[
  {
    "uid": "795906",
    "code": "BAE3213",
    "subject": "BAE",
    "number": "3213",
    "honors": false,
    "writingIntensive": false,
    "name": "Engineering Prin & Appl",
    "fullname": "Engineering Principles and Applications",
    "info": "Engineering principles/concepts. Students quantitatively apply mechanical/engineering principles to solve problems in animal production, crop production, horticulture, and soil/water management.",
    "prereq": []
  },
  {
    "uid": "004014",
    "code": "BAE4112W",
    "subject": "BAE",
    "number": "4112",
    "honors": false,
    "writingIntensive": true,
    "name": "Senior Design I",
    "fullname": "Senior Design I",
    "info": "Review of design concepts and process. Case studies involving engineering design. Discussion of safety/ethical issues. Develop proposal for senior design project (individual or group) to be completed in 4122. Oral presentation of written proposal.",
    "prereq": []
  },
  {
    "uid": "004015",
    "code": "BAE4122W",
    "subject": "BAE",
    "number": "4122",
    "honors": false,
    "writingIntensive": true,
    "name": "Senior Design II",
    "fullname": "Senior Design II",
    "info": "Complete design project started in 4112. Report, poster, and oral presentation of final design.",
    "prereq": []
  }
]