[
  {
    "uid": "0102081",
    "code": "FOST 10",
    "subject": "FOST",
    "number": "10",
    "name": "Study Abroad",
    "fullname": "Study Abroad",
    "info": "This no-credit registration allows students to maintain their University of Minnesota status while studying abroad.",
    "prereq": []
  },
  {
    "uid": "0168441",
    "code": "FOST 1040",
    "subject": "FOST",
    "number": "1040",
    "name": "Study Abroad",
    "fullname": "Study Abroad",
    "info": "Course used to grant credit for a new study abroad course or program that, by the time recruiting begins, has not had time to go through the normal approval process.",
    "prereq": []
  },
  {
    "uid": "0167581",
    "code": "FOST 1050",
    "subject": "FOST",
    "number": "1050",
    "name": "Study Abroad: UMN System",
    "fullname": "Study Abroad Through UMN System",
    "info": "",
    "prereq": []
  },
  {
    "uid": "0148471",
    "code": "FOST 1110",
    "subject": "FOST",
    "number": "1110",
    "name": "HECUA PROGRAMS",
    "fullname": "HECUA-Sponsored Study Abroad Programs",
    "info": "Course used to credit coursework taken abroad through programs of the Higher Education Consortium for Urban Affairs.",
    "prereq": []
  },
  {
    "uid": "0148291",
    "code": "FOST 1120",
    "subject": "FOST",
    "number": "1120",
    "name": "CIC PROGRAMS",
    "fullname": "CIC-Sponsored Study Abroad Programs",
    "info": "Courses used to credit coursework taken through study abroad programs of the Committee on Institutional Cooperation.",
    "prereq": []
  },
  {
    "uid": "0148371",
    "code": "FOST 1130",
    "subject": "FOST",
    "number": "1130",
    "name": "IES PROGRAMS",
    "fullname": "IES-Sponsored Study Abroad Programs",
    "info": "Course used to credit study abroad through programs of the Institute for the International Education of Students (IES).",
    "prereq": []
  },
  {
    "uid": "0148911",
    "code": "FOST 1140",
    "subject": "FOST",
    "number": "1140",
    "name": "CIEE PROGRAMS",
    "fullname": "CIEE-Sponsored Study Abroad Programs",
    "info": "Course used to credit study abroad through programs of the Council on International Educational Exchange.",
    "prereq": []
  },
  {
    "uid": "0130451",
    "code": "FOST 1150",
    "subject": "FOST",
    "number": "1150",
    "name": "Study Abroad Butler/IFSA",
    "fullname": "Butler/IFSA-Sponsored Study Abroad Programs",
    "info": "Course used to award credit for work successfully completed in Butler/IFSA-sponsored study abroad programs.",
    "prereq": []
  },
  {
    "uid": "0169211",
    "code": "FOST 1160",
    "subject": "FOST",
    "number": "1160",
    "name": "Study Abroad: Arcadia/CEA",
    "fullname": "Arcadia/CEA Study Abroad Programs",
    "info": "Credit for work completed in study abroad programs sponsored by Arcadia College/CEA for study abroad and cosponsored by the University of Minnesota.",
    "prereq": []
  },
  {
    "uid": "0148941",
    "code": "FOST 1180",
    "subject": "FOST",
    "number": "1180",
    "name": "BOLOGNA PROGRAM",
    "fullname": "Bologna Cooperative Studies Program, Italy",
    "info": "Course used to credit study abroad through the Bologna Cooperative Studies Program at the University of Bologna, Italy..",
    "prereq": []
  },
  {
    "uid": "0130411",
    "code": "FOST 1190",
    "subject": "FOST",
    "number": "1190",
    "name": "AESOP PRGRMS ABROAD",
    "fullname": "Study Abroad through other Big Ten Universities under CIC's AESOP",
    "info": "Course used to award credit for work successfully completed in study abroad programs sponsored by other Big Ten universities and cosponsored by the University of Minnesota through AESOP, a study abroad \\\"common market\\\" arrangement of the Committee on Institutional Cooperation.",
    "prereq": []
  },
  {
    "uid": "0110301",
    "code": "FOST 120",
    "subject": "FOST",
    "number": "120",
    "name": "Study Abroad",
    "fullname": "Study Abroad",
    "info": "Same as 0010; for program of full-time study abroad.",
    "prereq": []
  },
  {
    "uid": "7953101",
    "code": "FOST 1201",
    "subject": "FOST",
    "number": "1201",
    "name": "Study Abroad",
    "fullname": "Study Abroad",
    "info": "Not published in catalog.",
    "prereq": []
  },
  {
    "uid": "7953111",
    "code": "FOST 1202",
    "subject": "FOST",
    "number": "1202",
    "name": "Study Abroad",
    "fullname": "Study Abroad",
    "info": "Not published in catalog.\n\nprereq: dept consent",
    "prereq": []
  },
  {
    "uid": "7953121",
    "code": "FOST 1203",
    "subject": "FOST",
    "number": "1203",
    "name": "Study Abroad",
    "fullname": "Study Abroad",
    "info": "Not published in course catalog.\n\nprereq: dept consent",
    "prereq": []
  },
  {
    "uid": "7953131",
    "code": "FOST 1204",
    "subject": "FOST",
    "number": "1204",
    "name": "Study Abroad",
    "fullname": "Study Abroad",
    "info": "Not published in catalog.\n\nprereq: dept consent",
    "prereq": []
  },
  {
    "uid": "7953141",
    "code": "FOST 1205",
    "subject": "FOST",
    "number": "1205",
    "name": "Study Abroad",
    "fullname": "Study Abroad",
    "info": "Not published in catalog.\n\nprereq: dept consent",
    "prereq": []
  },
  {
    "uid": "7953151",
    "code": "FOST 1206",
    "subject": "FOST",
    "number": "1206",
    "name": "Study Abroad",
    "fullname": "Study Abroad",
    "info": "Not published in catalog.\n\nprereq: dept consent",
    "prereq": []
  },
  {
    "uid": "7953161",
    "code": "FOST 1207",
    "subject": "FOST",
    "number": "1207",
    "name": "Study Abroad",
    "fullname": "Study Abroad",
    "info": "Not published in catalog.\n\nprereq: dept consent",
    "prereq": []
  },
  {
    "uid": "7953171",
    "code": "FOST 1208",
    "subject": "FOST",
    "number": "1208",
    "name": "Study Abroad",
    "fullname": "Study Abroad",
    "info": "Not published in course catalog.\n\nprereq: dept consent",
    "prereq": []
  },
  {
    "uid": "7953181",
    "code": "FOST 1209",
    "subject": "FOST",
    "number": "1209",
    "name": "Study Abroad",
    "fullname": "Study Abroad",
    "info": "Not published in catalog.\n\nprereq: dept consent",
    "prereq": []
  },
  {
    "uid": "0168451",
    "code": "FOST 1250",
    "subject": "FOST",
    "number": "1250",
    "name": "Study at the Univ of Oslo",
    "fullname": "Study at the University of Oslo",
    "info": "Course used to award credit for work successfully completed in study abroad programs sponsored by the University of Oslo, Norway, and cosponsored by the University of Minnesota.",
    "prereq": []
  },
  {
    "uid": "0148991",
    "code": "FOST 1260",
    "subject": "FOST",
    "number": "1260",
    "name": "U KANSAS PROGRAMS",
    "fullname": "University of Kansas Study Abroad Programs",
    "info": "Course used to credit study abroad through programs sponsored by the University of Kansas and cosponsored by the University of Minnesota..",
    "prereq": []
  },
  {
    "uid": "0149011",
    "code": "FOST 1270",
    "subject": "FOST",
    "number": "1270",
    "name": "DIS PROGRAM",
    "fullname": "Denmark's International Study Program",
    "info": "Course used to credit study abroad in Denmark or Iceland through Denmark's International Study program..",
    "prereq": []
  },
  {
    "uid": "0130471",
    "code": "FOST 1280",
    "subject": "FOST",
    "number": "1280",
    "name": "MSU: AKITA,JAPAN",
    "fullname": "Minnesota State Universities Campus in Akita, Japan",
    "info": "Quarter, Year, or Summer Study in Minnesota State University-Akita, Japan.  Japanese language and area studies courses plus lower division general education courses.  Instruction in English.",
    "prereq": []
  },
  {
    "uid": "0130431",
    "code": "FOST 1310",
    "subject": "FOST",
    "number": "1310",
    "name": "MONTPELLIER SEM/YR",
    "fullname": "Study Abroad in Montpellier",
    "info": "Semester or year at Universit? Paul Val?ry, Montpellier, France, sponsored by Global Campus and the Department of French and Italian.  Students take regular courses and/or special courses for foreigners all taught entirely in French by Paul Val?ry faculty.  Many disciplines available.",
    "prereq": []
  },
  {
    "uid": "0149071",
    "code": "FOST 1320",
    "subject": "FOST",
    "number": "1320",
    "name": "TOLEDO PROGRAM",
    "fullname": "International Program in Toledo, Spain",
    "info": "Course used to credit study through the International Program of Spanish, European, and Latin American Studies in Toledo, Spain.",
    "prereq": []
  },
  {
    "uid": "0132321",
    "code": "FOST 1330",
    "subject": "FOST",
    "number": "1330",
    "name": "Study Abroad: Venezuela",
    "fullname": "Study Abroad in Venezuela",
    "info": "Semester or summer study in Venezuela through a University of Minnesota program administered by Global Campus and VENUSA. Spanish language, Venezuelan/Latin American studies.",
    "prereq": []
  },
  {
    "uid": "0167591",
    "code": "FOST 1340",
    "subject": "FOST",
    "number": "1340",
    "name": "Study Abroad: London",
    "fullname": "Study Abroad in London",
    "info": "Study Abroad in London",
    "prereq": []
  },
  {
    "uid": "7904301",
    "code": "FOST 1350",
    "subject": "FOST",
    "number": "1350",
    "name": "MELBOURNE SEM/YR",
    "fullname": "Study Abroad in Melbourne",
    "info": "Semester or year at University of Melbourne, Australia, sponsored by Global Studies. Students take regular or special courses for foreigners.  Many disciplines available.",
    "prereq": []
  },
  {
    "uid": "7907611",
    "code": "FOST 1360",
    "subject": "FOST",
    "number": "1360",
    "name": "Study Abroad: Lancaster Univ",
    "fullname": "Study Abroad at Lancaster University, England",
    "info": "Work at University of Lancaster, England, through study abroad sponsored by University of Minnesota.",
    "prereq": []
  },
  {
    "uid": "7912001",
    "code": "FOST 1370",
    "subject": "FOST",
    "number": "1370",
    "name": "Study Abroad: InterStudy",
    "fullname": "Study Abroad through InterStudy",
    "info": "Credit for work completed in study abroad program cosponsored by InterStudy and the University.",
    "prereq": []
  },
  {
    "uid": "0111271",
    "code": "FOST 1400",
    "subject": "FOST",
    "number": "1400",
    "name": "Study Abroad",
    "fullname": "Study Abroad",
    "info": "Course taken through study abroad that counts toward the Liberal Education graduation requirements as a Designated Theme in Cultural Diversity.\n\nprereq: dept consent",
    "prereq": []
  },
  {
    "uid": "0111331",
    "code": "FOST 1410",
    "subject": "FOST",
    "number": "1410",
    "name": "Study Abroad",
    "fullname": "Study Abroad",
    "info": "Course taken through study abroad that counts toward the Liberal Education graduation requirements as a Designated Theme in Citizenship and Public Ethics.\n\nprereq: dept consent",
    "prereq": []
  },
  {
    "uid": "0111641",
    "code": "FOST 1420",
    "subject": "FOST",
    "number": "1420",
    "name": "Study Abroad",
    "fullname": "Study Abroad",
    "info": "Course taken through study abroad that counts toward the Liberal Education graduation requirements as a Designated Theme in The Environment.\n\nprereq: dept consent",
    "prereq": []
  },
  {
    "uid": "0111661",
    "code": "FOST 1430",
    "subject": "FOST",
    "number": "1430",
    "name": "Study Abroad",
    "fullname": "Study Abroad",
    "info": "Course taken through study abroad that counts toward the Liberal Education graduation requirements as a Designated Theme in International Perspectives.\n\nprereq: dept consent",
    "prereq": []
  },
  {
    "uid": "0111681",
    "code": "FOST 1440",
    "subject": "FOST",
    "number": "1440",
    "name": "Study Abroad",
    "fullname": "Study Abroad",
    "info": "Course taken through study abroad that counts toward the Liberal Education graduation requirements as two Designated Themes, in Cultural Diversity and Citizenship and Public Ethics.\n\nprereq: dept consent",
    "prereq": []
  },
  {
    "uid": "7903511",
    "code": "FOST 1450",
    "subject": "FOST",
    "number": "1450",
    "name": "Study Abroad",
    "fullname": "Study Abroad",
    "info": "N/A\n\nprereq: dept consent",
    "prereq": []
  },
  {
    "uid": "0111711",
    "code": "FOST 1460",
    "subject": "FOST",
    "number": "1460",
    "name": "Study Abroad",
    "fullname": "Study Abroad",
    "info": "Course taken through study abroad that counts toward the Liberal Education graduation requirements as two Designated Themes, in Cultural Diversity and International Perspectives.\n\nprereq: dept consent",
    "prereq": []
  },
  {
    "uid": "0111731",
    "code": "FOST 1470",
    "subject": "FOST",
    "number": "1470",
    "name": "Study Abroad",
    "fullname": "Study Abroad",
    "info": "Course taken through study abroad that counts toward the Liberal Education graduation requirements as two Designated Themes, in Citizenship and Public Ethics and The Environment.\n\nprereq: dept consent",
    "prereq": []
  },
  {
    "uid": "0111751",
    "code": "FOST 1480",
    "subject": "FOST",
    "number": "1480",
    "name": "Study Abroad",
    "fullname": "Study Abroad",
    "info": "Course taken through study abroad that counts toward the Libral Education graduation requirements as two Designated Themes, in Citizenship and Public Ethics and International Perspectives.\n\nprereq: dept consent",
    "prereq": []
  },
  {
    "uid": "0111771",
    "code": "FOST 1490",
    "subject": "FOST",
    "number": "1490",
    "name": "Study Abroad",
    "fullname": "Study Abroad",
    "info": "Course taken through study abroad that counts toward the Liberal Education graduation requirements as two Designated Themes, in The Environment and International Perspectives.\n\nprereq: dept consent",
    "prereq": []
  },
  {
    "uid": "8072571",
    "code": "FOST 1495",
    "subject": "FOST",
    "number": "1495",
    "name": "Study Abroad",
    "fullname": "Study Abroad Course",
    "info": "Study abroad course.",
    "prereq": []
  },
  {
    "uid": "0111791",
    "code": "FOST 1500",
    "subject": "FOST",
    "number": "1500",
    "name": "Study Abroad",
    "fullname": "Study Abroad",
    "info": "Course taken through study abroad that counts toward the Liberal Education graduation requirements as a Diversified Core in Arts and Humanities.\n\nprereq: dept consent",
    "prereq": []
  },
  {
    "uid": "8203141",
    "code": "FOST 1501",
    "subject": "FOST",
    "number": "1501",
    "name": "The United States Post-WW2 Era",
    "fullname": "The United States in the Post-WW2 Era",
    "info": "This course is designed as a survey of US history since the Second World War, from the prosperous post-war period of the 1950s to the forty years between the election of JFK in 1960 and the election of Barack Obama in 2008, which mark one of the most turbulent periods in American history. Radical changes occurred during these decades in American political, social, and cultural life, changes which still have repercussions on American society today. Through a variety of readings, seminars, discussions, and research papers, as well as screenings of feature films, documentaries, and musical albums, the course aims at evoking the four decades for the purpose of arriving at a deeper understanding of the major events that took place during the period. A complete understanding of the transformational nature of these events is not possible, however, without placing them within the context of political and social history, and most especially within the framework of the larger interpretive principles of the culture which American Studies offers.",
    "prereq": []
  },
  {
    "uid": "8205581",
    "code": "FOST 1502",
    "subject": "FOST",
    "number": "1502",
    "name": "Americ. Popular Music Post WW2",
    "fullname": "Introduction to Popular Music - Many a Voice to Sing With: American Popular Music Since World War II",
    "info": "This course examines the historical significance of popular music in the United States from the mid twentieth century to the present.\n\nEthnomusicologist Alan Lomax stated, “As we live, so do we sing.” Those words have never been more applicable to the plight of the African American who came to America as slaves. We will examine a variety of musical genres beginning with the music of West Africa and moving to Plantations songs (spirituals, work songs), and a variety of musical genres ranging from the blues, rhythm and blues, country, folk, soul, rock, disco, and hip-hop. As we examine the various genres we will need to identify some of the individuals who were instrumental in shaping the landscape of what became American popular music. Such figures as Woody Guthrie, Bessie Smith, Duke Ellington, Buddy Holly, Robert Johnson, Ma Rainey, Elvis Presley, Stevie Wonder, James Brown, Bob Dylan, Joan Baez, Peter, Paul and Mary, Bruce Springsteen, Lauryn Hill, Tracy Chapman, and Jay-Z and many others. All of these individuals helped to shape and define the American popular music scene. All of the musical innovations and opportunities experienced by them are tempered by social, political, economic, and religious variables.\n\nAs we progress through each era, we will examine many of the social, economic, religious, political, and technological variables that influenced the direction of the music. For example, Jim Crow laws, the church, the Civil Rights Movements, the student, the anti-war movement, the environment protection and the Women’s Liberation movements, (anti)-Globalization, all played a major role in how the music was influenced. This course will also consider the global impact American pop music has had on the direction and influences of various musical styles and the economic force it has had on the global economy. The diversity dimensions for this course will be Race, Religion, and Gender. This will be the reoccurring theme throughout the semester as we examine the various developments and contributions of African Americans.",
    "prereq": []
  },
  {
    "uid": "0112191",
    "code": "FOST 1510",
    "subject": "FOST",
    "number": "1510",
    "name": "Study Abroad",
    "fullname": "Study Abroad",
    "info": "Course taken through study abroad that counts toward the Liberal Education graduation requirements as a diversified core in Biological Science with Lab.\n\nprereq: dept consent",
    "prereq": []
  },
  {
    "uid": "0112211",
    "code": "FOST 1520",
    "subject": "FOST",
    "number": "1520",
    "name": "Study Abroad",
    "fullname": "Study Abroad",
    "info": "Course taken through study abroad that counts toward the Liberal Education graduation requirements as a diversified core in Biological Science without Lab.\n\nprereq: dept consent",
    "prereq": []
  },
  {
    "uid": "0112221",
    "code": "FOST 1530",
    "subject": "FOST",
    "number": "1530",
    "name": "Study Abroad",
    "fullname": "Study Abroad",
    "info": "Course taken through study abroad that counts toward the Liberal Education graduation requirements as a Diversified Core in Historical Perspective.\n\nprereq: dept consent",
    "prereq": []
  },
  {
    "uid": "0112251",
    "code": "FOST 1540",
    "subject": "FOST",
    "number": "1540",
    "name": "Study Abroad",
    "fullname": "Study Abroad",
    "info": "Course taken through study abroad that counts toward the Liberal Education graduation requirements as a Diversified Core in Literature.\n\nprereq: dept consent",
    "prereq": []
  },
  {
    "uid": "0112261",
    "code": "FOST 1550",
    "subject": "FOST",
    "number": "1550",
    "name": "Study Abroad",
    "fullname": "Study Abroad",
    "info": "Course taken through study abroad that counts toward the Liberal Education graduation requirements as a Diversified Core in Mathematical Thinking.\n\nprereq: dept consent",
    "prereq": []
  },
  {
    "uid": "0112731",
    "code": "FOST 1560",
    "subject": "FOST",
    "number": "1560",
    "name": "Study Abroad",
    "fullname": "Study Abroad",
    "info": "Course taken through study abroad that counts toward the Liberal Education graduation requirements as a Diversified Core in Philosophical Perspective.\n\nprereq: dept consent",
    "prereq": []
  },
  {
    "uid": "0112751",
    "code": "FOST 1570",
    "subject": "FOST",
    "number": "1570",
    "name": "Study Abroad",
    "fullname": "Study Abroad",
    "info": "Course taken through study abroad that counts toward the Liberal Education graduation requirements as a Diversified Core in Physical Science with Lab.\n\nprereq: dept consent",
    "prereq": []
  },
  {
    "uid": "0112761",
    "code": "FOST 1580",
    "subject": "FOST",
    "number": "1580",
    "name": "Study Abroad",
    "fullname": "Study Abroad",
    "info": "Course taken through study abroad that counts toward the Liberal Education graduation requirements as a Diversified Core in Physical Science without Lab.\n\nprereq: dept consent",
    "prereq": []
  },
  {
    "uid": "0112791",
    "code": "FOST 1590",
    "subject": "FOST",
    "number": "1590",
    "name": "Study Abroad",
    "fullname": "Study Abroad",
    "info": "Course taken through study abroad that counts toward the Liberal Education graduation requirement as a Diversified Core in Social Science.\n\nprereq: dept consent",
    "prereq": []
  },
  {
    "uid": "0112801",
    "code": "FOST 1600",
    "subject": "FOST",
    "number": "1600",
    "name": "Study Abroad",
    "fullname": "Study Abroad",
    "info": "Course taken through study abroad that counts toward the Liberal Education graduation requirements as a Diversified Core in Visual or Performing Arts.\n\nprereq: dept consent",
    "prereq": []
  },
  {
    "uid": "0113421",
    "code": "FOST 1710",
    "subject": "FOST",
    "number": "1710",
    "name": "Study Abroad",
    "fullname": "Study Abroad",
    "info": "Course taken through study abroad that counts toward the Liberal Education graduation requirements as a Diversified Core in Arts and Humanities and a Designated Theme in Cultural Diversity.\n\nprereq: dept consent",
    "prereq": []
  },
  {
    "uid": "0113551",
    "code": "FOST 1720",
    "subject": "FOST",
    "number": "1720",
    "name": "Study Abroad",
    "fullname": "Study Abroad",
    "info": "Course taken through study abroad that counts toward the Liberal Education graduation requirements as a Diversified Core in Historical Perspective and  a Designated Theme in Cultural Diversity.\n\nprereq: dept consent",
    "prereq": []
  },
  {
    "uid": "0113561",
    "code": "FOST 1730",
    "subject": "FOST",
    "number": "1730",
    "name": "Study Abroad",
    "fullname": "Study Abroad",
    "info": "Course taken through study abroad that counts toward the Liberal Education graduation requirements as Diversified Core in Literature and Cultural Diversity.\n\nprereq: dept consent",
    "prereq": []
  },
  {
    "uid": "0113591",
    "code": "FOST 1740",
    "subject": "FOST",
    "number": "1740",
    "name": "Study Abroad",
    "fullname": "Study Abroad",
    "info": "Course taken through study abroad that counts toward the Liberal Education graduation requirements as a Diversified Core in Social Science and Cultural Diversity.\n\nprereq: dept consent",
    "prereq": []
  },
  {
    "uid": "0113601",
    "code": "FOST 1750",
    "subject": "FOST",
    "number": "1750",
    "name": "Study Abroad",
    "fullname": "Study Abroad",
    "info": "Course taken through study abroad that counts toward the Liberal Education graduation requirements as a Diversified Core in Arts and Humanities and a Designated Theme in Citizenship and Public Ethics.\n\nprereq: dept consent",
    "prereq": []
  },
  {
    "uid": "0114891",
    "code": "FOST 1760",
    "subject": "FOST",
    "number": "1760",
    "name": "Study Abroad",
    "fullname": "Study Abroad",
    "info": "Course taken through study abroad that counts toward the Liberal Education graduation requirements as a Diversified Core in Biological Science with Lab and a Designated Theme in Citizenship and Public Ethics.\n\nprereq: dept consent",
    "prereq": []
  },
  {
    "uid": "0115771",
    "code": "FOST 1770",
    "subject": "FOST",
    "number": "1770",
    "name": "Study Abroad",
    "fullname": "Study Abroad",
    "info": "Course taken through study abroad that counts toward the Liberal Education graduation requirements as a Diversified Core in Historical Perspective and a Designated Theme in Citizenship and Public Ethics.\n\nprereq: dept consent",
    "prereq": []
  },
  {
    "uid": "0115781",
    "code": "FOST 1780",
    "subject": "FOST",
    "number": "1780",
    "name": "Study Abroad",
    "fullname": "Study Abroad",
    "info": "Course taken through study abroad that counts toward the Liberal Education graduation requirements as a Diversified Core in Philosophical Perspective and a designated Theme in Citizenship and Public Ethics.\n\nprereq: dept consent",
    "prereq": []
  },
  {
    "uid": "0115821",
    "code": "FOST 1790",
    "subject": "FOST",
    "number": "1790",
    "name": "Study Abroad",
    "fullname": "Study Abroad",
    "info": "Course taken through study abroad that counts toward the Liberal Education graduation requirements as a Diversified core in Social Science and Citizenship and Public Ethics.\n\nprereq: dept consent",
    "prereq": []
  },
  {
    "uid": "0115841",
    "code": "FOST 1800",
    "subject": "FOST",
    "number": "1800",
    "name": "Study Abroad",
    "fullname": "Study Abroad",
    "info": "Course taken through study abroad that counts toward the Liberal Education graduation requirements as a Diversified Core in Arts and Humanities and a Designated Theme in The Environment.\n\nprereq: dept consent",
    "prereq": []
  },
  {
    "uid": "0117911",
    "code": "FOST 1810",
    "subject": "FOST",
    "number": "1810",
    "name": "Study Abroad",
    "fullname": "Study Abroad",
    "info": "Course taken through study abroad that counts toward the Liberal education graduation requirements as a Diversified Core in Biological Science with a Lab and a Designated Theme in The Environment.\n\nprereq: dept consent",
    "prereq": []
  },
  {
    "uid": "0117931",
    "code": "FOST 1820",
    "subject": "FOST",
    "number": "1820",
    "name": "Study Abroad",
    "fullname": "Study Abroad",
    "info": "Course taken through study abroad that counts toward the Liberal Education graduation requirements as a Diversified Core in Biological Science without Lab and a Designated Theme in The Environment.\n\nprereq: dept consent",
    "prereq": []
  },
  {
    "uid": "0117941",
    "code": "FOST 1830",
    "subject": "FOST",
    "number": "1830",
    "name": "Study Abroad",
    "fullname": "Study Abroad",
    "info": "Course taken through study abroad that counts toward the Liberal Education graduation requirements as a Diversified Core in Historical Perspective and a Designated Theme in The Environment.\n\nprereq: dept consent",
    "prereq": []
  },
  {
    "uid": "0117951",
    "code": "FOST 1840",
    "subject": "FOST",
    "number": "1840",
    "name": "Study Abroad",
    "fullname": "Study Abroad",
    "info": "Course taken through study abroad that counts toward the liberal Education graduation requirements as a Diversified core in Physical Science with Lab and a Designated Theme in The Environment.\n\nprereq: dept consent",
    "prereq": []
  },
  {
    "uid": "0117961",
    "code": "FOST 1850",
    "subject": "FOST",
    "number": "1850",
    "name": "Study Abroad",
    "fullname": "Study Abroad",
    "info": "Course taken through study abroad that counts toward the Liberal Education graduation requirements as a Diversified Core in Physical Science without Lab and a Designated Theme in The Environment.\n\nprereq: dept consent",
    "prereq": []
  },
  {
    "uid": "0117971",
    "code": "FOST 1860",
    "subject": "FOST",
    "number": "1860",
    "name": "Study Abroad",
    "fullname": "Study Abroad",
    "info": "Course taken through study abroad that counts toward the Liberal Education graduation requirements as a Diversified Core in Social Science and a Designated Theme in The Environment.\n\nprereq: dept consent",
    "prereq": []
  },
  {
    "uid": "0117981",
    "code": "FOST 1870",
    "subject": "FOST",
    "number": "1870",
    "name": "Study Abroad",
    "fullname": "Study Abroad",
    "info": "Course taken through study abroad that counts toward the Liberal Education graduation requirements as a Diversified Core in Arts and Humanities and a Designated Theme in International Perspectives.\n\nprereq: dept consent",
    "prereq": []
  },
  {
    "uid": "0117991",
    "code": "FOST 1880",
    "subject": "FOST",
    "number": "1880",
    "name": "Study Abroad",
    "fullname": "Study Abroad",
    "info": "Course taken through study abroad that counts toward the Liberal Education requirements for graduation as a Diversified Core in Historical Perspective and a Designated Theme in International Perspectives.\n\nprereq: dept consent",
    "prereq": []
  },
  {
    "uid": "0118001",
    "code": "FOST 1890",
    "subject": "FOST",
    "number": "1890",
    "name": "Study Abroad",
    "fullname": "Study Abroad",
    "info": "Course taken through study abroad that counts toward the Liberal Education graduation requirements as a Diversified Core in Literature and a Designated Theme in International Perspectives.\n\nprereq: dept consent",
    "prereq": []
  },
  {
    "uid": "0118011",
    "code": "FOST 1900",
    "subject": "FOST",
    "number": "1900",
    "name": "Study Abroad",
    "fullname": "Study Abroad",
    "info": "Course taken through study abroad that counts toward the Liberal Education graduation requirements as a Diversified Core in Philosophical Perspective and a Designated Theme in International Perspectives.\n\nprereq: dept consent",
    "prereq": []
  },
  {
    "uid": "0118021",
    "code": "FOST 1910",
    "subject": "FOST",
    "number": "1910",
    "name": "Study Abroad",
    "fullname": "Study Abroad",
    "info": "Course taken through study abroad that counts toward the Liberal Education graduation requirements as a Diversified Core in Social Science and a Designated Theme in International Perspectives.\n\nprereq: dept consent",
    "prereq": []
  },
  {
    "uid": "0118031",
    "code": "FOST 1920",
    "subject": "FOST",
    "number": "1920",
    "name": "Study Abroad",
    "fullname": "Study Abroad",
    "info": "Course taken through study abroad that counts toward the Liberal Education graduation requirements as a Diversified Core in Visual and Performing arts and a Designated Theme in International Perspectives.\n\nprereq: dept consent",
    "prereq": []
  },
  {
    "uid": "0102091",
    "code": "FOST 20",
    "subject": "FOST",
    "number": "20",
    "name": "Exchange Study Abroad",
    "fullname": "Exchange Study Abroad",
    "info": "        This no-credit registration allows students to maintain their University of Minnesota status while participating in an exchange program with a foreign university.",
    "prereq": []
  },
  {
    "uid": "0102241",
    "code": "FOST 3000",
    "subject": "FOST",
    "number": "3000",
    "name": "Study Abroad: Outside Program",
    "fullname": "Study Abroad: Outside Program",
    "info": "Study abroad outside program placeholder course.\n\nprereq: dept consent",
    "prereq": []
  },
  {
    "uid": "7967641",
    "code": "FOST 3010",
    "subject": "FOST",
    "number": "3010",
    "name": "Study Abroad: Directed Study",
    "fullname": "Directed Study Abroad",
    "info": "N/A",
    "prereq": []
  },
  {
    "uid": "0102251",
    "code": "FOST 3020",
    "subject": "FOST",
    "number": "3020",
    "name": "Study Abroad: Exchange Program",
    "fullname": "Exchange Study Abroad",
    "info": "N/A\n\nprereq: dept consent",
    "prereq": []
  },
  {
    "uid": "8078321",
    "code": "FOST 3021",
    "subject": "FOST",
    "number": "3021",
    "name": "Study Abroad: Bilateral Exchg",
    "fullname": "Study Abroad: Bilateral Exchange Program",
    "info": "Study abroad course",
    "prereq": []
  },
  {
    "uid": "8078331",
    "code": "FOST 3022",
    "subject": "FOST",
    "number": "3022",
    "name": "Study Abroad: China Center Ex.",
    "fullname": "Study Abroad: China Center Exchange Program",
    "info": "Study abroad course",
    "prereq": []
  },
  {
    "uid": "8078341",
    "code": "FOST 3023",
    "subject": "FOST",
    "number": "3023",
    "name": "Study Abroad: CSE Exchange",
    "fullname": "Study Abroad: CSE Exchange Program",
    "info": "Study abroad course",
    "prereq": []
  },
  {
    "uid": "8078351",
    "code": "FOST 3024",
    "subject": "FOST",
    "number": "3024",
    "name": "Study Abroad: Collegiate Exchg",
    "fullname": "Study Abroad: Collegiate Exchange Programs",
    "info": "study abroad course",
    "prereq": []
  },
  {
    "uid": "8078361",
    "code": "FOST 3025",
    "subject": "FOST",
    "number": "3025",
    "name": "Study Abroad: Scholarship Exch",
    "fullname": "Study Abroad: Scholarship / IRSEP Exchange Program",
    "info": "Study abroad course",
    "prereq": []
  },
  {
    "uid": "8078371",
    "code": "FOST 3026",
    "subject": "FOST",
    "number": "3026",
    "name": "Study Abroad: ISEP Exchange",
    "fullname": "Study Abroad: ISEP Exchange Program",
    "info": "Study abroad course",
    "prereq": []
  },
  {
    "uid": "8133121",
    "code": "FOST 3027",
    "subject": "FOST",
    "number": "3027",
    "name": "Study Abroad : Dept Affiliated",
    "fullname": "Study Abroad: Departmental Affiliated Program",
    "info": "Study abroad placeholder course.",
    "prereq": []
  },
  {
    "uid": "8160911",
    "code": "FOST 3028",
    "subject": "FOST",
    "number": "3028",
    "name": "Study Abroad: AC China Flagshp",
    "fullname": "Study Abroad: AC China Flagship Capstone Year Program",
    "info": "Study abroad placeholder course",
    "prereq": []
  },
  {
    "uid": "8195241",
    "code": "FOST 3029",
    "subject": "FOST",
    "number": "3029",
    "name": "Study Abroad: Dublin Program",
    "fullname": "Study Abroad: Study Abroad in Dublin",
    "info": "Similar to many already-existing courses (ex: FOST 3245 - Study Abroad: Morocco Program), this is a course shell that will be used as a placeholder course for the number of credits planned to take abroad that helps to ensure students maintain their student status and allows financial aid eligibility. Upon the student's return at the end of the program, this course will be removed from the student's record and replaced with actual, individual courses, credits and grades taken while abroad.",
    "prereq": []
  },
  {
    "uid": "8195251",
    "code": "FOST 3031",
    "subject": "FOST",
    "number": "3031",
    "name": "Study Abroad: U Copenhagen",
    "fullname": "Study Abroad: University Study in Copenhagen",
    "info": "Similar to many already-existing courses (ex: FOST 3245 - Study Abroad: Morocco Program), this is a course shell that will be used as a placeholder course for the number of credits planned to take abroad that helps to ensure students maintain their student status and allows financial aid eligibility. Upon the student's return at the end of the program, this course will be removed from the student's record and replaced with actual, individual courses, credits and grades taken while abroad.",
    "prereq": []
  },
  {
    "uid": "8195261",
    "code": "FOST 3032",
    "subject": "FOST",
    "number": "3032",
    "name": "Study Abroad: Jordan Program",
    "fullname": "Study Abroad: Study Abroad in Jordan",
    "info": "Similar to many already-existing courses (ex: FOST 3245 - Study Abroad: Morocco Program), this is a course shell that will be used as a placeholder course for the number of credits planned to take abroad that helps to ensure students maintain their student status and allows financial aid eligibility. Upon the student's return at the end of the program, this course will be removed from the student's record and replaced with actual, individual courses, credits and grades taken while abroad.",
    "prereq": []
  },
  {
    "uid": "8195271",
    "code": "FOST 3033",
    "subject": "FOST",
    "number": "3033",
    "name": "Study Abroad: Panama Program",
    "fullname": "Study Abroad: Summer Internships in Panama",
    "info": "Similar to many already-existing courses (ex: FOST 3245 - Study Abroad: Morocco Program), this is a course shell that will be used as a placeholder course for the number of credits planned to take abroad that helps to ensure students maintain their student status and allows financial aid eligibility. Upon the student's return at the end of the program, this course will be removed from the student's record and replaced with actual, individual courses, credits and grades taken while abroad.",
    "prereq": []
  },
  {
    "uid": "8195281",
    "code": "FOST 3034",
    "subject": "FOST",
    "number": "3034",
    "name": "Study Abroad: Barcelona Prgrm",
    "fullname": "Study Abroad: Study & Intern in Barcelona",
    "info": "Similar to many already-existing courses (ex: FOST 3245 - Study Abroad: Morocco Program), this is a course shell that will be used as a placeholder course for the number of credits planned to take abroad that helps to ensure students maintain their student status and allows financial aid eligibility. Upon the student's return at the end of the program, this course will be removed from the student's record and replaced with actual, individual courses, credits and grades taken while abroad.",
    "prereq": []
  },
  {
    "uid": "8195291",
    "code": "FOST 3035",
    "subject": "FOST",
    "number": "3035",
    "name": "Study Abroad: SOR CAPA BCLA",
    "fullname": "Study Abroad: SOR CAPA Barcelona",
    "info": "Similar to many already-existing courses (ex: FOST 3245 - Study Abroad: Morocco Program), this is a course shell that will be used as a placeholder course for the number of credits planned to take abroad that helps to ensure students maintain their student status and allows financial aid eligibility. Upon the student's return at the end of the program, this course will be removed from the student's record and replaced with actual, individual courses, credits and grades taken while abroad.",
    "prereq": []
  },
  {
    "uid": "8195301",
    "code": "FOST 3036",
    "subject": "FOST",
    "number": "3036",
    "name": "Study Abroad: SOR CET",
    "fullname": "Study Abroad: SOR CET",
    "info": "Similar to many already-existing courses (ex: FOST 3245 - Study Abroad: Morocco Program), this is a course shell that will be used as a placeholder course for the number of credits planned to take abroad that helps to ensure students maintain their student status and allows financial aid eligibility. Upon the student's return at the end of the program, this course will be removed from the student's record and replaced with actual, individual courses, credits and grades taken while abroad.",
    "prereq": []
  },
  {
    "uid": "8195311",
    "code": "FOST 3037",
    "subject": "FOST",
    "number": "3037",
    "name": "Study Abroad: U Study Italy",
    "fullname": "Study Abroad: University Study in Italy",
    "info": "Similar to many already-existing courses (ex: FOST 3245 - Study Abroad: Morocco Program), this is a course shell that will be used as a placeholder course for the number of credits planned to take abroad that helps to ensure students maintain their student status and allows financial aid eligibility. Upon the student's return at the end of the program, this course will be removed from the student's record and replaced with actual, individual courses, credits and grades taken while abroad.",
    "prereq": []
  },
  {
    "uid": "8195321",
    "code": "FOST 3038",
    "subject": "FOST",
    "number": "3038",
    "name": "Study Abroad: SOR CAPA HKNG",
    "fullname": "Study Abroad: SOR CAPA Hong Kong",
    "info": "Similar to many already-existing courses (ex: FOST 3245 - Study Abroad: Morocco Program), this is a course shell that will be used as a placeholder course for the number of credits planned to take abroad that helps to ensure students maintain their student status and allows financial aid eligibility. Upon the student's return at the end of the program, this course will be removed from the student's record and replaced with actual, individual courses, credits and grades taken while abroad.",
    "prereq": []
  },
  {
    "uid": "8195331",
    "code": "FOST 3039",
    "subject": "FOST",
    "number": "3039",
    "name": "Study Abroad: Hong Kong Prgrm",
    "fullname": "Study Abroad: Study & Intern in Hong Kong",
    "info": "Similar to many already-existing courses (ex: FOST 3245 - Study Abroad: Morocco Program), this is a course shell that will be used as a placeholder course for the number of credits planned to take abroad that helps to ensure students maintain their student status and allows financial aid eligibility. Upon the student's return at the end of the program, this course will be removed from the student's record and replaced with actual, individual courses, credits and grades taken while abroad.",
    "prereq": []
  },
  {
    "uid": "0168461",
    "code": "FOST 3040",
    "subject": "FOST",
    "number": "3040",
    "name": "Study Abroad",
    "fullname": "Study Abroad",
    "info": "Course used to grant credit for a new study abroad course or program that, by the time recruiting begins, has not had time to go through the normal approval process.\n\nprereq: dept consent",
    "prereq": []
  },
  {
    "uid": "0167601",
    "code": "FOST 3050",
    "subject": "FOST",
    "number": "3050",
    "name": "Study Abroad: UMN System Prog",
    "fullname": "Study Abroad Through UMN System",
    "info": "Study abroad through program sponsored by Duluth,Morris, or Crookston campus.\n\nprereq: dept consent",
    "prereq": []
  },
  {
    "uid": "7967651",
    "code": "FOST 3060",
    "subject": "FOST",
    "number": "3060",
    "name": "Study Abroad: Global Seminar",
    "fullname": "Global Seminar",
    "info": "Short term study abroad program during May Session or winter break.",
    "prereq": []
  },
  {
    "uid": "0148251",
    "code": "FOST 3110",
    "subject": "FOST",
    "number": "3110",
    "name": "Study Abroad: HECUA",
    "fullname": "HECUA-Sponsored Study Abroad Programs",
    "info": "Study abroad through Higher Education Consortium for Urban Affairs.\n\nprereq: dept consent",
    "prereq": []
  },
  {
    "uid": "8120971",
    "code": "FOST 3111",
    "subject": "FOST",
    "number": "3111",
    "name": "Study Abroad: ICLP Program",
    "fullname": "Study Abroad: International Chinese Language Program",
    "info": "Study abroad placeholder course for new affiliate program, ICLP.",
    "prereq": []
  },
  {
    "uid": "8078381",
    "code": "FOST 3115",
    "subject": "FOST",
    "number": "3115",
    "name": "Study Abroad: Alliance Program",
    "fullname": "Study Abroad: Alliance Program",
    "info": "Study abroad course",
    "prereq": []
  },
  {
    "uid": "0148591",
    "code": "FOST 3120",
    "subject": "FOST",
    "number": "3120",
    "name": "Study Abroad: AESOP/CIC",
    "fullname": "AESOP/CIC-Study Abroad Programs",
    "info": "Study abroad through Committee on Institutional Cooperation.\n\nprereq: dept consent",
    "prereq": []
  },
  {
    "uid": "8078391",
    "code": "FOST 3125",
    "subject": "FOST",
    "number": "3125",
    "name": "Study Abroad: USIT Irish Study",
    "fullname": "Study Abroad: USIT Irish Studies Summer School Program",
    "info": "Study abroad course",
    "prereq": []
  },
  {
    "uid": "0148571",
    "code": "FOST 3130",
    "subject": "FOST",
    "number": "3130",
    "name": "Study Abroad: IES Program",
    "fullname": "IES-Study Abroad Program",
    "info": "Study abroad through Institute for the International Education of Students (IES).\n\nprereq: dept consent",
    "prereq": []
  },
  {
    "uid": "8078401",
    "code": "FOST 3135",
    "subject": "FOST",
    "number": "3135",
    "name": "Study Abroad: CET Programs",
    "fullname": "Study Abroad: CET Programs",
    "info": "Study abroad course",
    "prereq": []
  },
  {
    "uid": "0148921",
    "code": "FOST 3140",
    "subject": "FOST",
    "number": "3140",
    "name": "Study Abroad: CIEE program",
    "fullname": "CIEE-Study Abroad Program",
    "info": "Study abroad through Council on International Educational Exchange.\n\nprereq: dept consent",
    "prereq": []
  },
  {
    "uid": "0130461",
    "code": "FOST 3150",
    "subject": "FOST",
    "number": "3150",
    "name": "Study Abroad: Butler Program",
    "fullname": "Butler/IFSA: Study Abroad Program",
    "info": "Study abroad sponsored by Butler University/IFSA and cosponsored by the University of Minnesota.\n\nprereq: dept consent",
    "prereq": []
  },
  {
    "uid": "0169221",
    "code": "FOST 3160",
    "subject": "FOST",
    "number": "3160",
    "name": "Study Abroad: Arcadia Program",
    "fullname": "Arcadia/CEA: Study Abroad Program",
    "info": "Study abroad sponsored by Arcadia College/CEA and cosponsored by the University of Minnesota.\n\nprereq: dept consent",
    "prereq": []
  },
  {
    "uid": "7978841",
    "code": "FOST 3170",
    "subject": "FOST",
    "number": "3170",
    "name": "Study Abroad: Freiburg",
    "fullname": "Study Abroad: Integrated Studies in Freiburg",
    "info": "Study Abroad placeholder course for the Integrated Studies in Freiburg program.",
    "prereq": []
  },
  {
    "uid": "8160921",
    "code": "FOST 3175",
    "subject": "FOST",
    "number": "3175",
    "name": "Study Abroad: AC China Flagshp",
    "fullname": "Study Abroad: AC China Flagship Capstone Year Program",
    "info": "Study abroad course",
    "prereq": []
  },
  {
    "uid": "0148951",
    "code": "FOST 3180",
    "subject": "FOST",
    "number": "3180",
    "name": "Study Abroad: Bologna Program",
    "fullname": "Bologna Cooperative Studies Program, Italy",
    "info": "Study abroad through Bologna Cooperative Studies Program at the University of Bologna, Italy.\n\nprereq: dept consent",
    "prereq": []
  },
  {
    "uid": "0130421",
    "code": "FOST 3190",
    "subject": "FOST",
    "number": "3190",
    "name": "AESOP Programs Abroad",
    "fullname": "Study Abroad through other Big Ten Universities under CIC's AESOP",
    "info": "Course used to award credit for work successfully completed in study abroad programs sponsored by other Big Ten universities and cosponsored by the University of Minnesota through AESOP, a study abroad \\\"common market\\\" arrangement of the Committee on Institutional Cooperation.",
    "prereq": []
  },
  {
    "uid": "7893881",
    "code": "FOST 3201",
    "subject": "FOST",
    "number": "3201",
    "name": "Study Abroad",
    "fullname": "Study Abroad",
    "info": "Course used to grant credit for a new study abroad course or program that, by the time recruiting begins, has not had time to go through the normal approval process.\n\nprereq: dept consent",
    "prereq": []
  },
  {
    "uid": "7893891",
    "code": "FOST 3202",
    "subject": "FOST",
    "number": "3202",
    "name": "Study Abroad",
    "fullname": "Study Abroad",
    "info": "Course used to grant credit for a new study abroad course or program that, by the time recruiting begins, has not had time to go through the normal approval process.\n\nprereq: dept consent",
    "prereq": []
  },
  {
    "uid": "7894651",
    "code": "FOST 3203",
    "subject": "FOST",
    "number": "3203",
    "name": "Study Abroad",
    "fullname": "Study Abroad",
    "info": "Course used to grant credit for a new study abroad course or program that, by the time recruiting begins, has not had time to go through the normal approval process.\n\nprereq: dept consent",
    "prereq": []
  },
  {
    "uid": "7893991",
    "code": "FOST 3204",
    "subject": "FOST",
    "number": "3204",
    "name": "Study Abroad",
    "fullname": "Study Abroad",
    "info": "Course used to grant credit for a new study abroad course or program that, by the time recruiting begins, has not had time to go through the normal approval process.\n\nprereq: dept consent",
    "prereq": []
  },
  {
    "uid": "7894051",
    "code": "FOST 3205",
    "subject": "FOST",
    "number": "3205",
    "name": "Study Abroad",
    "fullname": "Study Abroad",
    "info": "Course used to grant credit for a new study abroad course or program that, by the time recruiting begins, has not had time to go through the normal approval process.\n\nprereq: dept consent",
    "prereq": []
  },
  {
    "uid": "7894081",
    "code": "FOST 3206",
    "subject": "FOST",
    "number": "3206",
    "name": "Study Abroad",
    "fullname": "Study Abroad",
    "info": "Course used to grant credit for a new study abroad course or program that, by the time recruiting begins, has not had time to go through the normal approval process.\n\nprereq: dept consent",
    "prereq": []
  },
  {
    "uid": "7894131",
    "code": "FOST 3207",
    "subject": "FOST",
    "number": "3207",
    "name": "Study Abroad",
    "fullname": "Study Abroad",
    "info": "Course used to grant credit for a new study abroad course or program that, by the time recruiting begins, has not had time to go through the normal approval process.\n\nprereq: dept consent",
    "prereq": []
  },
  {
    "uid": "7894201",
    "code": "FOST 3208",
    "subject": "FOST",
    "number": "3208",
    "name": "Study Abroad",
    "fullname": "Study Abroad",
    "info": "Course used to grant credit for a new study abroad course or program that, by the time recruiting begins, has not had time to go through the normal approval process.\n\nprereq: dept consent",
    "prereq": []
  },
  {
    "uid": "7894211",
    "code": "FOST 3209",
    "subject": "FOST",
    "number": "3209",
    "name": "Study Abroad",
    "fullname": "Study Abroad",
    "info": "Course used to grant credit for a new study abroad course or program that, by the time recruiting begins, has not had time to go through the normal approval process.\n\nprereq: dept consent",
    "prereq": []
  },
  {
    "uid": "7977371",
    "code": "FOST 3210",
    "subject": "FOST",
    "number": "3210",
    "name": "Study Abroad",
    "fullname": "Study Abroad",
    "info": "TBD",
    "prereq": []
  },
  {
    "uid": "7894221",
    "code": "FOST 3211",
    "subject": "FOST",
    "number": "3211",
    "name": "Study Abroad",
    "fullname": "Study Abroad",
    "info": "Course used to grant credit for a new study abroad course or program that, by the time recruiting begins, has not had time to go through the normal approval process.\n\nprereq: dept consent",
    "prereq": []
  },
  {
    "uid": "7953191",
    "code": "FOST 3212",
    "subject": "FOST",
    "number": "3212",
    "name": "Study Abroad",
    "fullname": "Study Abroad",
    "info": "Not published in catalog.\n\nprereq: dept consent",
    "prereq": []
  },
  {
    "uid": "7953201",
    "code": "FOST 3213",
    "subject": "FOST",
    "number": "3213",
    "name": "Study Abroad",
    "fullname": "Study Abroad",
    "info": "Not published in course catalog.\n\nprereq: dept consent",
    "prereq": []
  },
  {
    "uid": "7953211",
    "code": "FOST 3214",
    "subject": "FOST",
    "number": "3214",
    "name": "Study Abroad",
    "fullname": "Study Abroad",
    "info": "Not published in course catalog.\n\nprereq: dept consent",
    "prereq": []
  },
  {
    "uid": "7953221",
    "code": "FOST 3215",
    "subject": "FOST",
    "number": "3215",
    "name": "Study Abroad",
    "fullname": "Study Abroad",
    "info": "Not published in catalog.\n\nprereq: dept consent",
    "prereq": []
  },
  {
    "uid": "8013591",
    "code": "FOST 3220",
    "subject": "FOST",
    "number": "3220",
    "name": "Study Abroad: SIT Program",
    "fullname": "Study Abroad: SIT Program",
    "info": "TBD",
    "prereq": []
  },
  {
    "uid": "8093951",
    "code": "FOST 3225",
    "subject": "FOST",
    "number": "3225",
    "name": "Study Abroad: Lang Immer China",
    "fullname": "Study Abroad: Language Immersion in China",
    "info": "Study abroad course.",
    "prereq": []
  },
  {
    "uid": "8013601",
    "code": "FOST 3230",
    "subject": "FOST",
    "number": "3230",
    "name": "Study Abroad: SFS Program",
    "fullname": "Study Abroad: School for Field Studies (SFS) Program",
    "info": "TBD",
    "prereq": []
  },
  {
    "uid": "8093961",
    "code": "FOST 3235",
    "subject": "FOST",
    "number": "3235",
    "name": "Study Abroad: Uni Stdy Ireland",
    "fullname": "Study Abroad: University Study in Ireland",
    "info": "Study abroad course.",
    "prereq": []
  },
  {
    "uid": "8013611",
    "code": "FOST 3240",
    "subject": "FOST",
    "number": "3240",
    "name": "Study Abroad: U Study Norway",
    "fullname": "University Study in Norway",
    "info": "TBD",
    "prereq": []
  },
  {
    "uid": "8078411",
    "code": "FOST 3245",
    "subject": "FOST",
    "number": "3245",
    "name": "Study Abroad: Morocco Program",
    "fullname": "Study Abroad: Arabic Language and Culture in Morocco Program",
    "info": "Study abroad course",
    "prereq": []
  },
  {
    "uid": "0168471",
    "code": "FOST 3250",
    "subject": "FOST",
    "number": "3250",
    "name": "Study at the Univ of Oslo",
    "fullname": "Study at the University of Oslo",
    "info": "Course used to award credit for work successfully completed in study abroad programs sponsored by the University of Oslo, Norway, and cosponsored by the University of Minnesota.",
    "prereq": []
  },
  {
    "uid": "8078421",
    "code": "FOST 3255",
    "subject": "FOST",
    "number": "3255",
    "name": "Study Abroad: Buenos Aires",
    "fullname": "Study Abroad: Language and Culture in Buenos Aires Program",
    "info": "Study abroad course",
    "prereq": []
  },
  {
    "uid": "0149001",
    "code": "FOST 3260",
    "subject": "FOST",
    "number": "3260",
    "name": "U KANSAS PROGRAMS",
    "fullname": "University of Kansas Study Abroad Programs",
    "info": "Course used to credit study abroad through programs sponsored by the University of Kansas and cosponsored by the University of Minnesota..",
    "prereq": []
  },
  {
    "uid": "8078431",
    "code": "FOST 3265",
    "subject": "FOST",
    "number": "3265",
    "name": "Study Abroad: Florence",
    "fullname": "Study Abroad: Florence Program",
    "info": "Study abroad course",
    "prereq": []
  },
  {
    "uid": "0149021",
    "code": "FOST 3270",
    "subject": "FOST",
    "number": "3270",
    "name": "Study Abroad: DIS Program",
    "fullname": "Denmark's International Study Program",
    "info": "Study abroad in Denmark or Iceland through Denmark's international study program.\n\nprereq: dept consent",
    "prereq": []
  },
  {
    "uid": "8078441",
    "code": "FOST 3275",
    "subject": "FOST",
    "number": "3275",
    "name": "Study Abroad: Mexico",
    "fullname": "Study Abroad: Mexico Program",
    "info": "Study abroad course",
    "prereq": []
  },
  {
    "uid": "0130481",
    "code": "FOST 3280",
    "subject": "FOST",
    "number": "3280",
    "name": "MSU: AKITA,JAPAN",
    "fullname": "Minnesota State Universities Campus in Akita, Japan",
    "info": "Quarter, Year, or Summer Study in Minnesota State University-Akita, Japan.  Japanese language and area studies courses plus lower division general education courses.  Instruction in English.",
    "prereq": []
  },
  {
    "uid": "8078451",
    "code": "FOST 3285",
    "subject": "FOST",
    "number": "3285",
    "name": "Study Abroad: Rome",
    "fullname": "Study Abroad in Rome Program",
    "info": "Study abroad course",
    "prereq": []
  },
  {
    "uid": "8013621",
    "code": "FOST 3290",
    "subject": "FOST",
    "number": "3290",
    "name": "Study Abroad: U Study NZ",
    "fullname": "University Study in New Zealand",
    "info": "TBD",
    "prereq": []
  },
  {
    "uid": "8078461",
    "code": "FOST 3295",
    "subject": "FOST",
    "number": "3295",
    "name": "Study Abroad: Sydney",
    "fullname": "Study and Internships in Sydney Program",
    "info": "Study abroad course",
    "prereq": []
  },
  {
    "uid": "8093971",
    "code": "FOST 3305",
    "subject": "FOST",
    "number": "3305",
    "name": "Study Abroad: Turkey",
    "fullname": "Study Abroad: Turkey",
    "info": "Study abroad course.",
    "prereq": []
  },
  {
    "uid": "8105971",
    "code": "FOST 3306",
    "subject": "FOST",
    "number": "3306",
    "name": "Study Abroad: Madrid",
    "fullname": "Study Abroad: Study and Internships in Madrid",
    "info": "Study abroad placeholder course.",
    "prereq": []
  },
  {
    "uid": "0130441",
    "code": "FOST 3310",
    "subject": "FOST",
    "number": "3310",
    "name": "Study Abroad: Montpellier",
    "fullname": "Study Abroad in Montpellier",
    "info": "Semester or year at Université Paul Valéry, Montpellier, France, sponsored by Global Campus and the Department of French and Italian. Students take regular courses or special courses for foreigners. All courses taught entirely in French by Paul Valéry faculty. Many disciplines available.\n\nprereq: dept consent",
    "prereq": []
  },
  {
    "uid": "8078471",
    "code": "FOST 3315",
    "subject": "FOST",
    "number": "3315",
    "name": "Study Abroad: MSID Ecuador",
    "fullname": "Study Abroad: MSID Ecuador Program",
    "info": "Study abroad course",
    "prereq": []
  },
  {
    "uid": "8129781",
    "code": "FOST 3316",
    "subject": "FOST",
    "number": "3316",
    "name": "Study Abroad: Hlth/Soc Ecuador",
    "fullname": "Study Abroad: Health and Society in Ecuador",
    "info": "Study abroad placeholder course for the new program, \\\"Health and Society in Ecuador\\\"",
    "prereq": []
  },
  {
    "uid": "0149081",
    "code": "FOST 3320",
    "subject": "FOST",
    "number": "3320",
    "name": "Study Abroad: Toledo Program",
    "fullname": "International Program in Toledo, Spain",
    "info": "Study through International Program of Spanish, European, and Latin American Studies in Toledo, Spain.\n\nprereq: dept consent",
    "prereq": []
  },
  {
    "uid": "8078481",
    "code": "FOST 3325",
    "subject": "FOST",
    "number": "3325",
    "name": "Study Abroad: MSID India",
    "fullname": "Study Abroad: MSID India",
    "info": "Study abroad course",
    "prereq": []
  },
  {
    "uid": "8160931",
    "code": "FOST 3326",
    "subject": "FOST",
    "number": "3326",
    "name": "Study Abroad: MSID Thailand",
    "fullname": "Study Abroad: MSID Thailand",
    "info": "Study abroad course",
    "prereq": []
  },
  {
    "uid": "0132331",
    "code": "FOST 3330",
    "subject": "FOST",
    "number": "3330",
    "name": "Study Abroad: Venezuela",
    "fullname": "Study Abroad in Venezuela",
    "info": "Semester or summer study in Venezuela through a University of Minnesota program administered by Learning Abroad Center and VENUSA. Spanish language, Venezuelan/Latin American studies.\n\nprereq: dept consent",
    "prereq": []
  },
  {
    "uid": "8078491",
    "code": "FOST 3335",
    "subject": "FOST",
    "number": "3335",
    "name": "Study Abroad: MSID Kenya",
    "fullname": "Study Abroad: MSID Kenya",
    "info": "Study abroad course",
    "prereq": []
  },
  {
    "uid": "7895111",
    "code": "FOST 3340",
    "subject": "FOST",
    "number": "3340",
    "name": "Study Abroad: London",
    "fullname": "Study Abroad in London",
    "info": "TBD",
    "prereq": []
  },
  {
    "uid": "8078501",
    "code": "FOST 3345",
    "subject": "FOST",
    "number": "3345",
    "name": "Study Abroad: MSID Senegal",
    "fullname": "Study Abroad: MSID Senegal",
    "info": "Study abroad course",
    "prereq": []
  },
  {
    "uid": "7900201",
    "code": "FOST 3350",
    "subject": "FOST",
    "number": "3350",
    "name": "Study Abroad: Australian Univ",
    "fullname": "University Study in Australia",
    "info": "Not listed in catalog.",
    "prereq": []
  },
  {
    "uid": "8078511",
    "code": "FOST 3355",
    "subject": "FOST",
    "number": "3355",
    "name": "Study Abroad: Uni Stdy Israel",
    "fullname": "Study Abroad: University Study in Israel Program",
    "info": "Study abroad course",
    "prereq": []
  },
  {
    "uid": "7907621",
    "code": "FOST 3360",
    "subject": "FOST",
    "number": "3360",
    "name": "Study Abroad: UK University",
    "fullname": "University Study in the United Kingdom",
    "info": "Not printed in catalog.",
    "prereq": []
  },
  {
    "uid": "8078521",
    "code": "FOST 3365",
    "subject": "FOST",
    "number": "3365",
    "name": "Study Abroad: S Africa Uni Std",
    "fullname": "Study Abroad: University Study in South Africa Program",
    "info": "Study abroad course",
    "prereq": []
  },
  {
    "uid": "7912551",
    "code": "FOST 3370",
    "subject": "FOST",
    "number": "3370",
    "name": "Study Abroad: InterStudy Prog",
    "fullname": "Study Abroad Through InterStudy",
    "info": "Study abroad program cosponsored by InterStudy and the University.",
    "prereq": []
  },
  {
    "uid": "8078531",
    "code": "FOST 3375",
    "subject": "FOST",
    "number": "3375",
    "name": "Study Abroad: S Korea Uni Stdy",
    "fullname": "Study Abroad: University Study in South Korea Program",
    "info": "Study abroad course",
    "prereq": []
  },
  {
    "uid": "7974321",
    "code": "FOST 3380",
    "subject": "FOST",
    "number": "3380",
    "name": "Study Abroad: American U Cairo",
    "fullname": "Study Abroad: American University Cairo",
    "info": "Placeholder course for students studying at American University Cairo.",
    "prereq": []
  },
  {
    "uid": "8078541",
    "code": "FOST 3385",
    "subject": "FOST",
    "number": "3385",
    "name": "Study Abroad: Tanzania",
    "fullname": "Study Abroad in Tanzania Program",
    "info": "Study abroad course",
    "prereq": []
  },
  {
    "uid": "7967661",
    "code": "FOST 3390",
    "subject": "FOST",
    "number": "3390",
    "name": "Study Abroad: AustraLearn",
    "fullname": "Study Abroad: GlobaLinks, AustraLearn",
    "info": "Study abroad program sponsored by Australearn and approved by University of Minnesota.",
    "prereq": []
  },
  {
    "uid": "8031231",
    "code": "FOST 3391",
    "subject": "FOST",
    "number": "3391",
    "name": "Study Abroad: AsiaLearn",
    "fullname": "Study Abroad: GlobaLinks, AsiaLearn",
    "info": "Study abroad program sponsored by AsiaLearn and approved by University of Minnesota.",
    "prereq": []
  },
  {
    "uid": "8031241",
    "code": "FOST 3392",
    "subject": "FOST",
    "number": "3392",
    "name": "Study Abroad: EuroLearn",
    "fullname": "Study Abroad: GlobaLinks, EuroLearn",
    "info": "Study abroad program sponsored by EuroLearn and approved by University of Minnesota.",
    "prereq": []
  },
  {
    "uid": "0110291",
    "code": "FOST 3400",
    "subject": "FOST",
    "number": "3400",
    "name": "Study Abroad",
    "fullname": "Study Abroad",
    "info": "Course taken through study abroad that counts toward the Liberal Education graduation requirements as a Designated Theme in Cultural Diversity\n\nprereq: dept consent",
    "prereq": []
  },
  {
    "uid": "0111281",
    "code": "FOST 3410",
    "subject": "FOST",
    "number": "3410",
    "name": "Study Abroad",
    "fullname": "Study Abroad",
    "info": "Course taken through study abroad that counts toward the Liberal Education graduation requirements as a Designated Theme in Citizenship and Public Ethics.\n\nprereq: dept consent",
    "prereq": []
  },
  {
    "uid": "0111341",
    "code": "FOST 3420",
    "subject": "FOST",
    "number": "3420",
    "name": "Study Abroad",
    "fullname": "Study Abroad",
    "info": "Course taken through study abroad that counts toward the Liberal Education graduation requirements as a Designated Theme in the Environment.\n\nprereq: dept consent",
    "prereq": []
  },
  {
    "uid": "0111651",
    "code": "FOST 3430",
    "subject": "FOST",
    "number": "3430",
    "name": "Study Abroad",
    "fullname": "Study Abroad",
    "info": "Course taken through study abroad that counts toward the Liberal Education graduation requirements as a Designated Theme in International Perspectives.\n\nprereq: dept consent",
    "prereq": []
  },
  {
    "uid": "0111671",
    "code": "FOST 3440",
    "subject": "FOST",
    "number": "3440",
    "name": "Study Abroad",
    "fullname": "Study Abroad",
    "info": "Course taken through study abroad that counts toward the Liberal Education graduation requirements as two Designated Themes, in Cultural Diversity and Citizenship and Public Ethics.\n\nprereq: dept consent",
    "prereq": []
  },
  {
    "uid": "7903521",
    "code": "FOST 3450",
    "subject": "FOST",
    "number": "3450",
    "name": "Study Abroad",
    "fullname": "Study Abroad",
    "info": "N/A\n\nprereq: dept consent",
    "prereq": []
  },
  {
    "uid": "0111701",
    "code": "FOST 3460",
    "subject": "FOST",
    "number": "3460",
    "name": "Study Abroad",
    "fullname": "Study Abroad",
    "info": "Course taken through study abroad that counts toward the Liberal Education graduation requirements as two Designated Themes, in Cultural Diversity and International Perspectives.\n\nprereq: dept consent",
    "prereq": []
  },
  {
    "uid": "0111721",
    "code": "FOST 3470",
    "subject": "FOST",
    "number": "3470",
    "name": "Study Abroad",
    "fullname": "Study Abroad",
    "info": "Course taken through study abroad that counts toward the Liberal Education graduation requirements as two Designated Themes, in Citizenship and Public Ethics and The Environment.\n\nprereq: dept consent",
    "prereq": []
  },
  {
    "uid": "0111741",
    "code": "FOST 3480",
    "subject": "FOST",
    "number": "3480",
    "name": "Study Abroad",
    "fullname": "Study Abroad",
    "info": "Course taken through study abroad that counts toward the Liberal Education graduation requirements as two Designated Themes, in Citizenship and Public Ethics and International Perspectives.\n\nprereq: dept consent",
    "prereq": []
  },
  {
    "uid": "0111761",
    "code": "FOST 3490",
    "subject": "FOST",
    "number": "3490",
    "name": "Study Abroad",
    "fullname": "Study Abroad",
    "info": "Course taken through study abroad that counts toward the Liberal Education graduation requirements as two Designated Themes, in The Environment and International Perspectives.\n\nprereq: dept consent",
    "prereq": []
  },
  {
    "uid": "8072581",
    "code": "FOST 3495",
    "subject": "FOST",
    "number": "3495",
    "name": "Study Abroad",
    "fullname": "Study Abroad Course",
    "info": "Study abroad course.",
    "prereq": []
  },
  {
    "uid": "0111781",
    "code": "FOST 3500",
    "subject": "FOST",
    "number": "3500",
    "name": "Study Abroad",
    "fullname": "Study Abroad",
    "info": "Course taken through study abroad that counts toward the Liberal Education graduation requirements as a Diversified Core in Arts and Humanities.\n\nprereq: dept consent",
    "prereq": []
  },
  {
    "uid": "8204461",
    "code": "FOST 3501",
    "subject": "FOST",
    "number": "3501",
    "name": "Compar Stud: US & Chinese Film",
    "fullname": "Comparative Studies in US and Chinese Film",
    "info": "This course compares major issues, theories, and methods in Chinese and American cinema. The  course is organized around a series of keywords, comprising a living vocabulary of culture, power,  social change, identity, nationhood, and globalization. Through these and related terms, we will  analyze the construction of class, gender, politics and other relationships of power central to the  U.S. and Chinese society. Course materials are interdisciplinary and, in addition to film, will also  include history, cultural studies, fiction, and popular culture. Assignments include reading, writing,  discussion, and a field trip exploring public memory at the China National Film Museum in Beijing.  Students analyze similarities and differences between films produced in Hollywood and Beijing,  gaining a transnational understanding of film studies and a critical perspective on Chinese and  American film traditions. The course also has a strong cultural focus, highlighting the differences in  history, economy, social structure, and values systems in the two countries, as seen through the  prism of cinema. ",
    "prereq": []
  },
  {
    "uid": "8205411",
    "code": "FOST 3502",
    "subject": "FOST",
    "number": "3502",
    "name": "China & West Cultural Concepts",
    "fullname": "Chinese and Western Cross-Cultural Concepts",
    "info": "As political, economic, and social integration of China and Western cultures increases in the 21st century, it is increasingly vital that we attempt to attain a greater mutual understanding between East and West. One path to this goal is to make a comparative study of Chinese and Western core\nconcepts, taking advantage of the growing body of ethnological, sociological, and psychological evidence for cultural differences. Just as “Western culture” is not a monolithic category, so what it means to be “Chinese” is embedded in a larger, Eastern context. This course attempts to present a contrastive analysis of the defining concepts of Chinese and Western culture through the lens of different academic disciplines, including sociology, anthropology, language, semiotics cognitive science, and cross-cultural psychology. The approach is interdisciplinary and comparative, leading students to explore central concepts in Chinese and Western philosophy, values, interpersonal relationships, communication patterns, thinking, and behavioral norms. Emphasis will be on specific examples of various cultural phenomena, and will draw on both scientific research and illustrative informal data in order to generate classroom discussion and open analysis. ",
    "prereq": []
  },
  {
    "uid": "8205421",
    "code": "FOST 3503",
    "subject": "FOST",
    "number": "3503",
    "name": "Envr. Issue & Intl Cooperation",
    "fullname": "Environmental Issues and International Cooperation",
    "info": "The global environmental crisis is the planet’s biggest existential threat, and will have an incalculable impact on all societies and economies. For students interested in environmental policy, social impact, entrepreneurship, risk management, and sustainability, this course will provide a foundational understanding of the environmental policy decisions that will shape their future careers. With a focus\non US-China cooperation, the course will provide case studies of specific international accords and local regulations, as well as the latest scientific and technological advances. Upon completion of the course, students should have a grasp of such questions as how to determine the biggest environmental threats and opportunities, how to measure effectiveness of policy and business decisions, and how to conduct thoughtful, inclusive analysis. The curriculum will also include site visits in Beijing, and guest lectures from local environmental experts.",
    "prereq": []
  },
  {
    "uid": "0112181",
    "code": "FOST 3510",
    "subject": "FOST",
    "number": "3510",
    "name": "Study Abroad",
    "fullname": "Study Abroad",
    "info": "N/A\n\nprereq: dept consent",
    "prereq": []
  },
  {
    "uid": "0112201",
    "code": "FOST 3520",
    "subject": "FOST",
    "number": "3520",
    "name": "Study Abroad",
    "fullname": "Study Abroad",
    "info": "Course taken through study abroad that counts toward the Liberal Education graduation requirements as a diversified core in Biological Science without Lab.\n\nprereq: dept consent",
    "prereq": []
  },
  {
    "uid": "0112231",
    "code": "FOST 3530",
    "subject": "FOST",
    "number": "3530",
    "name": "Study Abroad",
    "fullname": "Study Abroad",
    "info": "Course taken through study abroad that counts toward the Liberal Education graduation requirements as Diversified Core in Historical Perspective.\n\nprereq: dept consent",
    "prereq": []
  },
  {
    "uid": "0112241",
    "code": "FOST 3540",
    "subject": "FOST",
    "number": "3540",
    "name": "Study Abroad",
    "fullname": "Study Abroad",
    "info": "Course taken through study abroad that counts toward the Liberal Education graduation requirements as a Diversified Core in Literature.\n\nprereq: dept consent",
    "prereq": []
  },
  {
    "uid": "0112271",
    "code": "FOST 3550",
    "subject": "FOST",
    "number": "3550",
    "name": "Study Abroad",
    "fullname": "Study Abroad",
    "info": "Course taken through study abroad that counts toward the Liberal Education graduation requirements as a Diversified Core in Mathematical Thinking.\n\nprereq: dept consent",
    "prereq": []
  },
  {
    "uid": "0112741",
    "code": "FOST 3560",
    "subject": "FOST",
    "number": "3560",
    "name": "Study Abroad",
    "fullname": "Study Abroad",
    "info": "Course taken through study abroad that counts toward the Liberal Education graduation requirements as a Diversified Core in Philosophical Perspective.\n\nprereq: dept consent",
    "prereq": []
  },
  {
    "uid": "0112821",
    "code": "FOST 3570",
    "subject": "FOST",
    "number": "3570",
    "name": "Study Abroad",
    "fullname": "Study Abroad",
    "info": "Course taken through study abroad that counts toward the Liberal Education graduation requirements as a Diversified Core in Physical Science with Lab.\n\nprereq: dept consent",
    "prereq": []
  },
  {
    "uid": "0112771",
    "code": "FOST 3580",
    "subject": "FOST",
    "number": "3580",
    "name": "Study Abroad",
    "fullname": "Study Abroad",
    "info": "Course taken through study abroad that counts toward the Liberal Education graduation requirements as a Diversified Core in Physical Science without Lab.\n\nprereq: dept consent",
    "prereq": []
  },
  {
    "uid": "0112781",
    "code": "FOST 3590",
    "subject": "FOST",
    "number": "3590",
    "name": "Study Abroad",
    "fullname": "Study Abroad",
    "info": "Course taken through study abroad that counts toward the Liberal Education graduation requirements as a Diversified Core in Social Science.\n\nprereq: dept consent",
    "prereq": []
  },
  {
    "uid": "0112811",
    "code": "FOST 3600",
    "subject": "FOST",
    "number": "3600",
    "name": "Study Abroad",
    "fullname": "Study Abroad",
    "info": "Course taken through study abroad that counts toward the Liberal Education graduation requirements as a Diversified Core in Visual or Performing Arts.\n\nprereq: dept consent",
    "prereq": []
  },
  {
    "uid": "0113531",
    "code": "FOST 3710",
    "subject": "FOST",
    "number": "3710",
    "name": "Study Abroad",
    "fullname": "Study Abroad",
    "info": "Course taken through study abroad that counts toward the Liberal Education graduation requirements as a Diversified Core in Arts and Humanities and a Designated Theme in Cultural Diversity.\n\nprereq: dept consent",
    "prereq": []
  },
  {
    "uid": "0113541",
    "code": "FOST 3720",
    "subject": "FOST",
    "number": "3720",
    "name": "Study Abroad",
    "fullname": "Study Abroad",
    "info": "Course taken through study abroad that counts toward the Liberal Education graduation requirements as a Diversified Core in Historical Perspective and a Designated Theme in Cultural Diversity.\n\nprereq: dept consent",
    "prereq": []
  },
  {
    "uid": "0113571",
    "code": "FOST 3730",
    "subject": "FOST",
    "number": "3730",
    "name": "Study Abroad",
    "fullname": "Study Abroad",
    "info": "Study Abroad\n\nprereq: dept consent",
    "prereq": []
  },
  {
    "uid": "0113581",
    "code": "FOST 3740",
    "subject": "FOST",
    "number": "3740",
    "name": "Study Abroad",
    "fullname": "Study Abroad",
    "info": "Course taken through study abroad that counts toward the Liberal Education graduation requirements as a Diversified Core in Social Science and Cultural Diversity.\n\nprereq: dept consent",
    "prereq": []
  },
  {
    "uid": "0113611",
    "code": "FOST 3750",
    "subject": "FOST",
    "number": "3750",
    "name": "Study Abroad",
    "fullname": "Study Abroad",
    "info": "Course taken through study abroad that counts toward the Liberal Education graduation requirements as a Diversified Core in Arts and Humanities and a Designated Theme in Citizenship and Public Ethics.\n\nprereq: dept consent",
    "prereq": []
  },
  {
    "uid": "0115751",
    "code": "FOST 3760",
    "subject": "FOST",
    "number": "3760",
    "name": "Study Abroad",
    "fullname": "Study Abroad",
    "info": "Course taken through study abroad that counts toward the Liberal Education graduation requirements as a Diversified Core in Biological Science With Lab and a Designated Theme in Citizenship and Public Ethics.\n\nprereq: dept consent",
    "prereq": []
  },
  {
    "uid": "0115761",
    "code": "FOST 3770",
    "subject": "FOST",
    "number": "3770",
    "name": "Study Abroad",
    "fullname": "Study Abroad",
    "info": "Course taken through study abroad that counts toward the Liberal Education graduation requirements as a Diversified core in Historical Perspective and a Designated Theme in Citizenship and Public Ethics.\n\nprereq: dept consent",
    "prereq": []
  },
  {
    "uid": "0115801",
    "code": "FOST 3780",
    "subject": "FOST",
    "number": "3780",
    "name": "Study Abroad",
    "fullname": "Study Abroad",
    "info": "Course taken through study abroad that counts toward the Liberal Education graduation requirements as a Diversified Core in Philosophical Perspective and a designated Theme in Citizenship and Public Ethics.\n\nprereq: dept consent",
    "prereq": []
  },
  {
    "uid": "0115811",
    "code": "FOST 3790",
    "subject": "FOST",
    "number": "3790",
    "name": "Study Abroad",
    "fullname": "Study Abroad",
    "info": "Course taken through study abroad that counts toward the Liberal Education graduation requirements as a Diversified Core in Social Science and Citizenship and Public Ethics.\n\nprereq: dept consent",
    "prereq": []
  },
  {
    "uid": "0115851",
    "code": "FOST 3800",
    "subject": "FOST",
    "number": "3800",
    "name": "Study Abroad",
    "fullname": "Study Abroad",
    "info": "Course taken through study abroad that counts toward the Liberal Education graduation requirements as a Diversified Core in Arts and Humanities and a Designated Theme in The Environment.\n\nprereq: dept consent",
    "prereq": []
  },
  {
    "uid": "0117921",
    "code": "FOST 3810",
    "subject": "FOST",
    "number": "3810",
    "name": "Study Abroad",
    "fullname": "Study Abroad",
    "info": "Course taken through study abroad that counts toward the Liberal education graduation requirements as a Diversified Core in Biological Science with a Lab and a Designated Theme in The Environment.\n\nprereq: dept consent",
    "prereq": []
  },
  {
    "uid": "0125771",
    "code": "FOST 3820",
    "subject": "FOST",
    "number": "3820",
    "name": "Study Abroad",
    "fullname": "Study Abroad",
    "info": "Course taken through study abroad that counts toward the Liberal Education graduation requirements as a Diversified Core in Biological Science without Lab and a Designated Theme in The Environment.\n\nprereq: dept consent",
    "prereq": []
  },
  {
    "uid": "0125781",
    "code": "FOST 3830",
    "subject": "FOST",
    "number": "3830",
    "name": "Study Abroad",
    "fullname": "Study Abroad",
    "info": "Course taken through study abroad that counts toward the Liberal Education graduation requirements as a Diversified Core in Historical Perspective and a Designated Theme in The Environment.\n\nprereq: dept consent",
    "prereq": []
  },
  {
    "uid": "0125791",
    "code": "FOST 3840",
    "subject": "FOST",
    "number": "3840",
    "name": "Study Abroad",
    "fullname": "Study Abroad",
    "info": "Course taken through study abroad that counts toward the liberal Education graduation requirements as a Diversified Core in Physical Science with Lab and a Designated Theme in The Environment.\n\nprereq: dept consent",
    "prereq": []
  },
  {
    "uid": "0125821",
    "code": "FOST 3850",
    "subject": "FOST",
    "number": "3850",
    "name": "Study Abroad",
    "fullname": "Study Abroad",
    "info": "Course taken through study abroad that counts toward the Liberal Education graduation requirements as a Diversified Core in Physical Science without Lab and a Designated Theme in The Environment.\n\nprereq: dept consent",
    "prereq": []
  },
  {
    "uid": "0125831",
    "code": "FOST 3860",
    "subject": "FOST",
    "number": "3860",
    "name": "Study Abroad",
    "fullname": "Study Abroad",
    "info": "Course taken through study abroad that counts toward the Liberal Education graduation requirements as a diversified Core in Social Science and a Designated Theme in The Environment.\n\nprereq: dept consent",
    "prereq": []
  },
  {
    "uid": "0125841",
    "code": "FOST 3870",
    "subject": "FOST",
    "number": "3870",
    "name": "Study Abroad",
    "fullname": "Study Abroad",
    "info": "Course taken through study abroad that counts toward the Liberal Education graduation requirements as a Diversified Core in Arts and Humanities and a Designated Theme in International Perspectives.\n\nprereq: dept consent",
    "prereq": []
  },
  {
    "uid": "0125851",
    "code": "FOST 3880",
    "subject": "FOST",
    "number": "3880",
    "name": "Study Abroad",
    "fullname": "Study Abroad",
    "info": "Course taken through study abroad that counts toward the Liberal Education requirements for graduation as a Diversified Core in Historical Perspective and a Designated Theme in International Perspectives.\n\nprereq: dept consent",
    "prereq": []
  },
  {
    "uid": "0125861",
    "code": "FOST 3890",
    "subject": "FOST",
    "number": "3890",
    "name": "Study Abroad",
    "fullname": "Study Abroad",
    "info": "Course taken through study abroad that counts toward the Liberal Education graduation requirements as a Diversified Core in Literature and a Designated Theme in International Perspectives.\n\nprereq: dept consent",
    "prereq": []
  },
  {
    "uid": "8203061",
    "code": "FOST 3896",
    "subject": "FOST",
    "number": "3896",
    "name": "Virtual Intl. Internship",
    "fullname": "Virtual International Internship",
    "info": "This course is designed to provide students with an opportunity to learn about the virtual international work environment by critically examining a professional, remote experience abroad through an intercultural lens. A key element to this course is to deepen students’ knowledge of their internship placement country’s professional norms and cultural context in comparison to other students’ internship placement countries, as well as the United States, and understand how COVID-19 has impacted these environments. Students’ research and writing on COVID-19 globally will include ethical analysis on how the national approach has impacted society, if they agree with this approach or not, and why. We will interrogate how this knowledge will influence their behavior in their society and the world. Students will also enhance their understanding of their chosen field using a global mindset.\n\nThe course is designed to guide students in the internship experience and create a foundation for a successful professional career as well as working to understand and articulate career skill outcomes. In addition to gaining a cross-cultural comparative view on work, the topics and assignments will deepen students’ insights about themselves, professional expectations, and being successful in the virtual workplace. Students are expected to make a valuable contribution to the virtual internship placement through the completion of projects and tasks guided by their internship supervisor in the placement country. This will require students to employ intercultural communication skills in a professional, virtual setting while critically examining their own worldview.\n\nThree Credit Course\nStudents who take the Virtual International Internship a second time will complete the three-credit version of this course and will be expected to complete the same number of hours at their internship sites as those who are taking the four-credit course. The academic work for the three-credit course will correspond to the second semester of internship participation in order to increase students’ remote, professional experience, strengthen their knowledge of their chosen industry, as well as enhance their global mind-set. The Global Perspectives liberal education requirement is not fulfilled by taking the three-credit version of this course.",
    "prereq": []
  },
  {
    "uid": "0118061",
    "code": "FOST 3900",
    "subject": "FOST",
    "number": "3900",
    "name": "Study Abroad",
    "fullname": "Study Abroad",
    "info": "Course taken through study abroad that counts toward the Liberal Education graduation requirements as a Diversified Core in Philosophical Perspective and a Designated Theme in International Perspectives.\n\nprereq: dept consent",
    "prereq": []
  },
  {
    "uid": "0118051",
    "code": "FOST 3910",
    "subject": "FOST",
    "number": "3910",
    "name": "Study Abroad",
    "fullname": "Study Abroad",
    "info": "Course taken through study abroad that counts toward the Liberal Education graduation requirements as a Diversified Core in Social Science and a Designated Theme in International Perspectives.\n\nprereq: dept consent",
    "prereq": []
  },
  {
    "uid": "0118041",
    "code": "FOST 3920",
    "subject": "FOST",
    "number": "3920",
    "name": "Study Abroad",
    "fullname": "Study Abroad",
    "info": "Course taken through study abroad that counts toward the Liberal Education graduation requirements as a Diversified core in Visual and Performing Arts and a Designated Theme in International Perspectives.\n\nprereq: dept consent",
    "prereq": []
  },
  {
    "uid": "8078551",
    "code": "FOST 3991",
    "subject": "FOST",
    "number": "3991",
    "name": "Study Abroad: SOR CAPA London",
    "fullname": "Study Abroad: SOR London Semester & Quarter Programs",
    "info": "Study abroad course",
    "prereq": []
  },
  {
    "uid": "8078561",
    "code": "FOST 3993",
    "subject": "FOST",
    "number": "3993",
    "name": "Study Abroad: SOR CAPA Sydney",
    "fullname": "Study Abroad: SOR CAPA Sydney",
    "info": "Study abroad course",
    "prereq": []
  },
  {
    "uid": "8078571",
    "code": "FOST 3994",
    "subject": "FOST",
    "number": "3994",
    "name": "Study Abroad: SOR CAPA ACU",
    "fullname": "Study Abroad: SOR CAPA Australian Catholic University",
    "info": "Study abroad course",
    "prereq": []
  },
  {
    "uid": "8078581",
    "code": "FOST 3995",
    "subject": "FOST",
    "number": "3995",
    "name": "Study Abroad: SOR DIS",
    "fullname": "Study Abroad: SOR DIS",
    "info": "Study abroad course",
    "prereq": []
  },
  {
    "uid": "8078591",
    "code": "FOST 3996",
    "subject": "FOST",
    "number": "3996",
    "name": "Study Abroad: SOR GlobaLinks",
    "fullname": "Study Abroad: SOR GlobaLinks",
    "info": "Study abroad course",
    "prereq": []
  },
  {
    "uid": "8078601",
    "code": "FOST 3997",
    "subject": "FOST",
    "number": "3997",
    "name": "Study Abroad: SOR Rome",
    "fullname": "Study Abroad: SOR Rome",
    "info": "Study abroad course",
    "prereq": []
  },
  {
    "uid": "8111911",
    "code": "FOST 3998",
    "subject": "FOST",
    "number": "3998",
    "name": "Study Abroad: SOR SFS",
    "fullname": "Study Abroad: SOR SFS",
    "info": "Study abroad course.",
    "prereq": []
  },
  {
    "uid": "8043251",
    "code": "FOST 3999",
    "subject": "FOST",
    "number": "3999",
    "name": "Study Abroad",
    "fullname": "Study Abroad",
    "info": "Study abroad for-credit internship course.",
    "prereq": []
  },
  {
    "uid": "7911071",
    "code": "FOST 5000",
    "subject": "FOST",
    "number": "5000",
    "name": "Study Abroad",
    "fullname": "Study Abroad",
    "info": "Study abroad registration.\n\nprereq: dept consent",
    "prereq": []
  },
  {
    "uid": "8066831",
    "code": "FOST 5010",
    "subject": "FOST",
    "number": "5010",
    "name": "Study Abroad: Directed Study",
    "fullname": "Study Abroad Directed Study placeholder course",
    "info": "Study abroad course.",
    "prereq": []
  },
  {
    "uid": "7941361",
    "code": "FOST 5020",
    "subject": "FOST",
    "number": "5020",
    "name": "Global Experience Program",
    "fullname": "Global Experience Program",
    "info": "The course is used to award credit for work successfully completed on the Global Experience Program study abroad internship program.  Evaluation standards and work load are determined by the graduate faculty member who signs the Global Experience Program learning contract required of each participant.  Number of contact hours varies from location to location.\n\nprereq: Must have graduate student status",
    "prereq": []
  },
  {
    "uid": "0102101",
    "code": "FOST 60",
    "subject": "FOST",
    "number": "60",
    "name": "Study Abroad",
    "fullname": "Study Abroad",
    "info": "Study abroad.",
    "prereq": []
  }
]