[
  {
    "code": "INAR 5100",
    "subject": "INAR",
    "id": "5100",
    "title": "Topics in Arch",
    "info": "topics specified in the class schedule.",
    "prereqInfo": "inar grad major or instr consent",
    "prereq": []
  },
  {
    "code": "INAR 8004",
    "subject": "INAR",
    "id": "8004",
    "title": "Method and Theory",
    "info": "survey and evaluation of archaeological approaches to non-literary, material evidence for past human activities and societies.",
    "prereqInfo": null,
    "prereq": []
  },
  {
    "code": "INAR 8100",
    "subject": "INAR",
    "id": "8100",
    "title": "Interdisc Seminar",
    "info": "review and evaluation of approaches to interdisciplinary research; themes vary.  leadership and research shared by staff, visitors, and students.",
    "prereqInfo": null,
    "prereq": []
  },
  {
    "code": "INAR 8200",
    "subject": "INAR",
    "id": "8200",
    "title": "Directed Readings",
    "info": "tbd",
    "prereqInfo": "inar grad major or instr consent",
    "prereq": []
  },
  {
    "code": "INAR 8300",
    "subject": "INAR",
    "id": "8300",
    "title": "Research",
    "info": "tbd",
    "prereqInfo": "inar grad major or instr consent",
    "prereq": []
  },
  {
    "code": "INAR 8333",
    "subject": "INAR",
    "id": "8333",
    "title": "FTE: Master's",
    "info": "(no description)",
    "prereqInfo": "master's student, adviser and dgs consent",
    "prereq": []
  },
  {
    "code": "INAR 8444",
    "subject": "INAR",
    "id": "8444",
    "title": "FTE: Doctoral",
    "info": "(no description)",
    "prereqInfo": "doctoral student, adviser and dgs consent",
    "prereq": []
  },
  {
    "code": "INAR 8666",
    "subject": "INAR",
    "id": "8666",
    "title": "Doct Pre-Thesis Cr*",
    "info": "tbd",
    "prereqInfo": "doctoral student who has not passed prelim oral; no required consent for 1st/2nd registrations, up to 12 combined cr; dept consent for 3rd/4th registrations, up to 24 combined cr; doctoral student admitted before summer 2007 may register up to four times, up to 60 combined cr",
    "prereq": {
      "code": "INAR 60",
      "subject": "INAR",
      "id": "60"
    }
  },
  {
    "code": "INAR 8777",
    "subject": "INAR",
    "id": "8777",
    "title": "Thesis Credit:Mast*",
    "info": "(no description)",
    "prereqInfo": "max 18 cr per semester or summer; 10 cr total required (plan a only)",
    "prereq": {
      "code": "INAR 10",
      "subject": "INAR",
      "id": "10"
    }
  },
  {
    "code": "INAR 8888",
    "subject": "INAR",
    "id": "8888",
    "title": "Thesis Credit:Doct*",
    "info": "(no description)",
    "prereqInfo": "max 18 cr per semester or summer; 24 cr required",
    "prereq": {}
  }
]