[{"code":"SKT 5001","subject":"SKT","id":"5001","title":"Beg. Sanskrit","info":"introduction to the classical language of ancient india.","prereqInfo":null,"prereq":[]},{"code":"SKT 5002","subject":"SKT","id":"5002","title":"Beg. Sanskrit","info":"introduction to the classical language of ancient india.","prereqInfo":null,"prereq":[]},{"code":"SKT 5201","subject":"SKT","id":"5201","title":"Interm. Sanskrit","info":"readings in sanskrit literature.","prereqInfo":null,"prereq":[]},{"code":"SKT 5202","subject":"SKT","id":"5202","title":"Int. Sanskrit","info":"readings in sanskrit literature.","prereqInfo":null,"prereq":[]},{"code":"SKT 5710","subject":"SKT","id":"5710","title":"Topics: Lang and Literature","info":"selected reading and/or study of linguistic problems in sanskrit.","prereqInfo":null,"prereq":[]},{"code":"SKT 5992","subject":"SKT","id":"5992","title":"Directed Readings","info":"guided individual reading or study.","prereqInfo":null,"prereq":[]},{"code":"SKT 8993","subject":"SKT","id":"8993","title":"Directed Studies","info":"guided individual reading or study.","prereqInfo":null,"prereq":[]}]