[
  {
    "code": "WHRE 3990",
    "subject": "WHRE",
    "id": "3990",
    "title": "Topics for Undergrads in WHRE",
    "info": "course content varies by offering.",
    "prereqInfo": null,
    "prereq": []
  },
  {
    "code": "WHRE 4990",
    "subject": "WHRE",
    "id": "4990",
    "title": "Topics: Professional Issues",
    "info": "course content varies by offering.",
    "prereqInfo": null,
    "prereq": []
  },
  {
    "code": "WHRE 5121",
    "subject": "WHRE",
    "id": "5121",
    "title": "Prin of Super. Mgmt.",
    "info": "introduction to the principles of supervision in education, business, industry, government, and service organizations.",
    "prereqInfo": null,
    "prereq": []
  },
  {
    "code": "WHRE 5628",
    "subject": "WHRE",
    "id": "5628",
    "title": "Multi Media Pres in Bus",
    "info": "designing, creating, and presenting information using multimedia resources in business settings.",
    "prereqInfo": null,
    "prereq": []
  },
  {
    "code": "WHRE 8333",
    "subject": "WHRE",
    "id": "8333",
    "title": "FTE: Master's",
    "info": "fte: master's",
    "prereqInfo": null,
    "prereq": []
  },
  {
    "code": "WHRE 8444",
    "subject": "WHRE",
    "id": "8444",
    "title": "FTE: Doctoral",
    "info": "(no description)",
    "prereqInfo": null,
    "prereq": []
  },
  {
    "code": "WHRE 8666",
    "subject": "WHRE",
    "id": "8666",
    "title": "Doct Pre-Thesis Cr",
    "info": "doctoral pre-thesis credits",
    "prereqInfo": null,
    "prereq": []
  },
  {
    "code": "WHRE 8777",
    "subject": "WHRE",
    "id": "8777",
    "title": "Thesis Credit: Mast*",
    "info": "thesis credits: master's",
    "prereqInfo": null,
    "prereq": []
  },
  {
    "code": "WHRE 8888",
    "subject": "WHRE",
    "id": "8888",
    "title": "Thesis Credit:Doct*",
    "info": "(no description)",
    "prereqInfo": null,
    "prereq": []
  },
  {
    "code": "WHRE 8913",
    "subject": "WHRE",
    "id": "8913",
    "title": "Interp Research",
    "info": "hermeneutic, ethnomethodological, and phenomenological research methodologies.  consideration of ethics, evaluation, and usefulness of interpretive research.  practice in conducting interpretive research in work, community, and family education.",
    "prereqInfo": null,
    "prereq": []
  },
  {
    "code": "WHRE 8914",
    "subject": "WHRE",
    "id": "8914",
    "title": "Critical Science Research",
    "info": "origins, influences, characteristics, and central concepts; distinction between critical science and other action research; requisite skills and knowledge for conducting critical science research and using that knowledge in a project.",
    "prereqInfo": null,
    "prereq": []
  }
]