[
  {
    "uid": "801123",
    "code": "DAKO1121",
    "subject": "DAKO",
    "number": "1121",
    "honors": false,
    "writing": false,
    "name": "Beg Dakota I",
    "fullname": "Beginning Dakota I",
    "info": "Listening, speaking, reading, writing. Oral drills, in-class participation focused on questions/answers.",
    "prereq": {}
  },
  {
    "uid": "801124",
    "code": "DAKO1122",
    "subject": "DAKO",
    "number": "1122",
    "honors": false,
    "writing": false,
    "name": "Beg Dakota II",
    "fullname": "Beginning Dakota II",
    "info": "Further development of language acquisiton skills. Oral drills, in-class participation focused on questions/answers.\n\nprereq: 1121",
    "prereq": {
      "and": [
        "801123"
      ]
    }
  },
  {
    "uid": "801125",
    "code": "DAKO3123",
    "subject": "DAKO",
    "number": "3123",
    "honors": false,
    "writing": false,
    "name": "Intermediate Dakota I",
    "fullname": "Intermediate Dakota I",
    "info": "Listening, speaking, reading, writing. Oral drills, in-class participation focused on questions/answers.\n\nprereq: 1122",
    "prereq": {
      "and": [
        "801124"
      ]
    }
  },
  {
    "uid": "801126",
    "code": "DAKO3124",
    "subject": "DAKO",
    "number": "3124",
    "honors": false,
    "writing": false,
    "name": "Int Dakota II",
    "fullname": "Intermediate Dakota II",
    "info": "Listening, speaking, reading, writing. Oral drills, in-class participation focused on questions/answers.\n\nprereq: 1121, 1122, 3123",
    "prereq": {
      "and": [
        "801123",
        "801124",
        "801125"
      ]
    }
  },
  {
    "uid": "804276",
    "code": "DAKO3125",
    "subject": "DAKO",
    "number": "3125",
    "honors": false,
    "writing": false,
    "name": "Into to Dakota Linguistics",
    "fullname": "Introduction to Dakota Linguistics",
    "info": "Structure of Dakota, including phonology, morphology, syntax, and semantics.\n\nprereq: 3124",
    "prereq": {
      "and": [
        "801126"
      ]
    }
  },
  {
    "uid": "807951",
    "code": "DAKO3126",
    "subject": "DAKO",
    "number": "3126",
    "honors": false,
    "writing": false,
    "name": "Dakota Language for the Class",
    "fullname": "Dakota Language for the Classroom",
    "info": "General/specialized language for core subjects, daily routines, and classroom discourse. Methods for teaching Dakota language.\n\nprereq: 1122",
    "prereq": {
      "and": [
        "801124"
      ]
    }
  },
  {
    "uid": "806396",
    "code": "DAKO3127",
    "subject": "DAKO",
    "number": "3127",
    "honors": false,
    "writing": false,
    "name": "Dakota Language for Teachers",
    "fullname": "Dakota Language for Teachers",
    "info": "Dakota language for teachers. Methods of teaching Dakota language in the classroom.\n\nprereq: 1121",
    "prereq": {
      "and": [
        "801123"
      ]
    }
  },
  {
    "uid": "802760",
    "code": "DAKO4121",
    "subject": "DAKO",
    "number": "4121",
    "honors": false,
    "writing": false,
    "name": "Beg Dakota I",
    "fullname": "Beginning Dakota I",
    "info": "Language acquisitions skills, oral drills. In-class participation focuses on questions/answers.\n\nprereq: [1122, 1004] in another language or passing score on LPE or grad student",
    "prereq": {
      "and": [
        "801124"
      ]
    }
  },
  {
    "uid": "801440",
    "code": "DAKO4122",
    "subject": "DAKO",
    "number": "4122",
    "honors": false,
    "writing": false,
    "name": "Beg Dakota II",
    "fullname": "Beginning Dakota II",
    "info": "Further development of language acquisition skills. Oral drills, in-class participation focused on questions and answers.\n\nprereq: [1121, 1004 in another language] or passing score on LPE or grad student",
    "prereq": {
      "and": [
        "801123"
      ]
    }
  },
  {
    "uid": "802761",
    "code": "DAKO4123",
    "subject": "DAKO",
    "number": "4123",
    "honors": false,
    "writing": false,
    "name": "Intermediate Dakota I",
    "fullname": "Intermediate Dakota I",
    "info": "Listening, speaking, reading, writing. Oral drills. In-class participation focuses on questions/answers.\n\nprereq: 1121, 3123, 5126",
    "prereq": {
      "and": [
        "801123",
        "801125",
        "800983"
      ]
    }
  },
  {
    "uid": "801441",
    "code": "DAKO4124",
    "subject": "DAKO",
    "number": "4124",
    "honors": false,
    "writing": false,
    "name": "Int Dakota II",
    "fullname": "Intermediate Dakota II",
    "info": "Listening, speaking, reading, writing. Oral drills. In-class participation focuses on questions/answers.\n\nprereq: 1121, 1122, 3123",
    "prereq": {
      "and": [
        "801123",
        "801124",
        "801125"
      ]
    }
  },
  {
    "uid": "802750",
    "code": "DAKO4126",
    "subject": "DAKO",
    "number": "4126",
    "honors": false,
    "writing": false,
    "name": "Advanced Dakota Language I",
    "fullname": "Advanced Dakota Language I",
    "info": "Focuses on immersion method.",
    "prereq": {}
  },
  {
    "uid": "802996",
    "code": "DAKO4129",
    "subject": "DAKO",
    "number": "4129",
    "honors": false,
    "writing": false,
    "name": "Advanced Dakota Language II",
    "fullname": "Advanced Dakota Language II",
    "info": "Focuses on immersion method.",
    "prereq": {}
  },
  {
    "uid": "800983",
    "code": "DAKO5126",
    "subject": "DAKO",
    "number": "5126",
    "honors": false,
    "writing": false,
    "name": "Advanced Dakota Language I",
    "fullname": "Advanced Dakota Language I",
    "info": "Focuses on immersion method.",
    "prereq": {}
  },
  {
    "uid": "800984",
    "code": "DAKO5129",
    "subject": "DAKO",
    "number": "5129",
    "honors": false,
    "writing": false,
    "name": "Advanced Dakota Language II",
    "fullname": "Advanced Dakota Language II",
    "info": "Focuses on immersion method.",
    "prereq": {}
  },
  {
    "uid": "817996",
    "code": "DAKO5226",
    "subject": "DAKO",
    "number": "5226",
    "honors": false,
    "writing": false,
    "name": "Dakota Mastery I",
    "fullname": "Dakota Mastery I",
    "info": "This content-based Dakota language class will focus on Dakota culture and history. Students will learn through both oral and written texts. Both traditional and contemporary stories will be discussed and utilized to give students a better view of Dakota ontology and epistemology. The effects of colonization and the need for decolonization will be also be discussed through the lens of Dakota stories and culture.",
    "prereq": {}
  },
  {
    "uid": "819098",
    "code": "DAKO5229",
    "subject": "DAKO",
    "number": "5229",
    "honors": false,
    "writing": false,
    "name": "Dakota Mastery II",
    "fullname": "Dakota Mastery II",
    "info": "This content-based Dakota language class will focus on Dakota culture and history. Students will learn through both oral and written texts. Both traditional and contemporary stories will be discussed and utilized to give students a better view of Dakota ontology and epistemology. The effects of colonization and the need for decolonization will be also be discussed through the lens of Dakota stories and culture.",
    "prereq": {}
  }
]